Workbook
Name Apps_Stategy: #REF!
Name AREA_TO_PASTE1: 'RFQ Data'!$A$1
Name AREA_TO_PASTE2: PRICE!$A$1
Name AREA_TO_PASTE3: 'PROCESS & CAPEX'!$A$1
Name COEFF_1: PRICE!$T$63
Name COEFF_2: PRICE!$T$64
Name COEFF_3: PRICE!$T$65
Name Cur_rate: 'Small runner-PRICE'!$C$6
Name CUR_RM_Index: '[1]RFQ Data'!$K$24
Name Data5_Agressivity: PRICE!$O$58
Name INDEX_IMPACT: 'PROCESS & CAPEX'!$M$13:$M$26
Name PRICE_inCUR: PRICE!$N$51
Name QuotingCUR: 'RFQ Data'!$H$20
Name SIMUL_INDEXATION: 'PROCESS & CAPEX'!$L$13:$L$26
Name SIMUL_NEWRATE: PRICE!$AU$7
Name SIMUL_PRICE: PRICE!$W$7
Name SIMUL_VOL: PRICE!$Y$41
Name SIMUL_VOL_PRODUCTIVITY: PRICE!$AO$2:$AS$3
Name Small_Runner_Zone: 'Small runner-PRICE'!$D$32,'Small runner-PRICE'!$D$10:$D$15
Name Strategy_type: #REF!
Name Target_price: 'RFQ Data'!$C$11
Name Trader: #REF!
Name User1: #REF!
Name user3: #REF!
Name User4: #REF!

Sheet RFQ Data
B1: Requester | C1: Mark Z. | F1: RFQ DATA - Costing process | J1: RFQ# | L1: 25626-BRU-00
C2: Sales has provided the following information | I2: Costing leader | L2: FRANCIS
B3: Project | C3: Riyong/RY5.578.100A | I3: Type of product line | L3: Brushes
B4: Customer Name | C4: Riyong | I4: Application | L4: HVAC blowers
B5: Customer location | C5: China | I5: Stategic segment ? | J5: YES | L5: Comfort & Auxiliary motors
I6: Type of process | L6: B-Alt & Auxilairy / t or a
B7: Customer area | C7: China + South pacific | E7: Zone | F7: 1
B8: Target price | C8: 0 | D8: RMB | E8: in Currency of customer Area
B9: Target price | C9: 0 | D9: RMB | E9: In Currency of AVO manufacturing plant | J9: Package volume
B10: exchange rate : | C10: 1 | D10: RMBRMB | E10: We are selling in the expected currency, this is a good news | J10: 500 | K10: Kparts
D11: SOP
B12: Years | C12: 2025 | D12: 2026 | E12: 2027 | F12: 2028 | G12: 2029 | H12: 2030 | J12: Business link
B13: Qty (Kp) | C13: 0 | D13: 500 | E13: 500 | F13: 500 | G13: 500 | H13: 500 | J13: 0 | K13: of average yearly sales
B14: Productivity plan | C14: 0 | D14: 0 | E14: 0 | F14: 0 | G14: 0 | H14: 0 | I14: or | J14: 0 | K14: kRMB
B15: Target price | C15: 0 | D15: 0 | E15: 0 | F15: 0 | G15: 0 | H15: 0 | J15: to pay at tooling order
B16: Capacity to set up | C16: 0 | D16: 600 | E16: 600 | F16: 600 | G16: 600 | H16: 600
A17: Definition of the manufacturing location
A18: For | C18: China + South pacific | D18: the strategy for | G18: B-Alt & Auxilairy / t or a | H18: is to finish the product in | J18: Tianjin | K18: in zone | L18: 1
A19: Because the delivery takes place in | E19: same | F19: zone, recommandation is | H19: DDP | I19: China
A20: For this plant our normal terms of payment are | E20: 60 | F20: days the plant invoices in | H20: RMB | I20: 0 | J20: payment term negociated (days)
A21: As delivery conditions quoted | C21: EXW | F21: we consider a customer pick up every | G21: 2 | H21: EUR | I21: RMB | J21: USD | K21: INR | L21: KWON
A22: we will keep a safety stock of | D22: 7 | E22: days of averge customer forecast | H22: 0.125 | I22: 1 | J22: 0.1375 | K22: 11.875 | L22: 0.195
A23: We consider that the leadtime within a the same zone is | F23: 1 | H23: second currency : | J23: EURRMB | K23: 8
G24: INDEXATION : Product includes… | J24: EURRMB | K24: 8
A25: These parameters lead to the following levels of inventory | G25: Copper | H25: 8.65 | I25: EUR | J25: /kg | K25: Material cost only (LME)
B26: Semi-finished product in transit /AVOplants | E26: 6.4603843 | F26: w days* | G26: Silver | H26: 1137 | I26: EUR | J26: /kg | K26: Material cost only (LME)
B27: Finished product safety stock in house | E27: 7 | G27: Nat Graphite | H27: 2.7764034 | I27: EUR | J27: /kg
B28: AvG Finsished product in house to cover pick up | E28: 9.3333333 | G28: Art Graphite | H28: 7.5 | I28: EUR | J28: /kg
B29: Finished product in transit to the customer | E29: 0 | G29: Mix with Nat | H29: 3.1937069 | I29: EUR | J29: /kg | K29: RM cost of black-mix /nat. graph.
B30: Finished product at customer | E30: 0 | G30: Mix with Art | H30: 7.256 | I30: EUR | J30: /kg | K30: RM cost of black-mix /art. graph.
B31: Total finished product inventory | E31: 22.793718 | F31: days | H31: 0 | I31: EUR | J31: /kg
B32: w days* = weighted days = days x %price | G32: Other mix | H32: 22 | I32: EUR | J32: /kg | K32: Price is adjusted /quoted grade
B33: The WIP in the plant considers | E33: 7 | F33: days of RM | G33: Plate | H33: 90 | I33: EUR | J33: /kg | K33: Price is adjusted /quoted grade
H34: 0 | I34: EUR | J34: /kg
O64: =IF(G64<>0,H64/G64*(1-'RFQ Data'!$I$36),0) -> 0
O65: =IF(G65<>0,H65/G65*(1-'RFQ Data'!$I$36),0) -> 0
O66: =IF(G66<>0,H66/G66*(1-'RFQ Data'!$I$36),0) -> 0
O67: =IF(G67<>0,H67/G67*(1-'RFQ Data'!$I$36),0) -> 0
O68: =IF(G68<>0,H68/G68*(1-'RFQ Data'!$I$36),0) -> 0
O69: =IF(G69<>0,H69/G69*(1-'RFQ Data'!$I$36),0) -> 0
O70: =IF(G70<>0,H70/G70*(1-'RFQ Data'!$I$36),0) -> 0
O71: =IF(G71<>0,H71/G71*(1-'RFQ Data'!$I$36),0) -> 0
O72: =IF(G72<>0,H72/G72*(1-'RFQ Data'!$I$36),0) -> 0
O73: =IF(G73<>0,H73/G73*(1-'RFQ Data'!$I$36),0) -> 0
O74: =IF(G74<>0,H74/G74*(1-'RFQ Data'!$I$36),0) -> 0
O75: =IF(G75<>0,H75/G75*(1-'RFQ Data'!$I$36),0) -> 0
... O91: =IF(G91<>0,H91/G91*(1-'RFQ Data'!$I$36),0) -> 0

Sheet PRICE
A1: Profitability from COSTING | B1: 2025 | C1: 2026 | D1: 2027 | E1: 2028 | F1: 2029 | G1: 2030 | H1: 2031 | K1: TRI / ROI result | L1: 0.30009445 | M1: 0.3 | N1: ROI target | Q1: Riyong/RY5.578.100A Riyong China | S1: I | T1: Limit of frozen data | V1: SIMULATION ZONE | AA1: =Q1 -> Riyong/RY5.578.100A Riyong China | AC1: Profitability (SIMULATION) | AD1: 2023 | AE1: 2024 | AF1: 2025 | AG1: 2026 | AH1: 2027 | AI1: 2028 | AJ1: 2029 | AM1: I | AN1: NEW | AO1: =AE1 -> 2024 | AP1: =AF1 -> 2025 | AQ1: =AG1 -> 2026 | AR1: =AH1 -> 2027 | AS1: =AI1 -> 2028 | AU1: Average | AW1: I | AX1: Profitability (SIMULATION) | AY1: 2023 | AZ1: 2024 | BA1: 2025 | BB1: 2026 | BC1: 2027 | BD1: 2028 | BE1: 2029
A2: Qtes | B2: 0 | C2: 500 | D2: 500 | E2: 500 | F2: 500 | G2: 500 | H2: 0 | I2: 500 | K2: Cash Generation | L2: 0 | O2: RFQ# | Q2: 25626-BRU-00 | S2: I | Y2: RFQ# | AA2: =Q2 -> 25626-BRU-00 | AC2: Qtes | AD2: 0 | AE2: =IF(AO2="",C2,AO2) -> 500 | AF2: =IF(AP2="",D2,AP2) -> 500 | AG2: =IF(AQ2="",E2,AQ2) -> 500 | AH2: =IF(AR2="",F2,AR2) -> 500 | AI2: =IF(AS2="",G2,AS2) -> 500 | AJ2: 0 | AM2: I | AN2: volume | AT2: Kparts | AU2: =AVERAGE(AE2:AI2) -> 500 | AW2: I | AX2: Qtes | AY2: =AD2 -> 0 | AZ2: =AE2 -> 500 | BA2: =AF2 -> 500 | BB2: =AG2 -> 500 | BC2: =AH2 -> 500 | BD2: =AI2 -> 500 | BE2: =AJ2 -> 0
A3: Productivity | B3: 0 | C3: 0 | D3: 0 | E3: 0 | F3: 0 | G3: 0 | H3: 0 | K3: VAN | L3: 0.018335211 | N3: ROI target changed | Q3: #VALUE! | S3: I | T3: ADJUST THE PRICE TO FINAL PRICE TARGETTED | AC3: Productivity | AD3: =B3 -> 0 | AE3: =IF(AO3="",C3,AO3) -> 0 | AF3: =IF(AP3="",D3,AP3) -> 0 | AG3: =IF(AQ3="",E3,AQ3) -> 0 | AH3: =IF(AR3="",F3,AR3) -> 0 | AI3: =IF(AS3="",G3,AS3) -> 0 | AJ3: =H3 -> 0 | AM3: I | AN3: productivity | AT3: % | AW3: I | AX3: Productivity | AY3: =AD3 -> 0 | AZ3: =AE3 -> 0 | BA3: =AF3 -> 0 | BB3: =AG3 -> 0 | BC3: =AH3 -> 0 | BD3: =AI3 -> 0 | BE3: =AJ3 -> 0
A4: Part impacted by productivity | B4: 0.91768565 | C4: 0.91768565 | D4: 0.91768565 | E4: 0.91768565 | F4: 0.91768565 | G4: 0.91768565 | H4: 0.91768565 | Q4: Calculation OK | S4: I | T4: Initial Target price (RFQ data) | W4: ='RFQ Data'!C9 -> 0 | X4: ='RFQ Data'!D9 -> RMB | Y4: Avo plant currency | AC4: Part impacted by productivity | AD4: =AD7-AD6-AD5 -> -0.41544772 | AE4: =AD4*(1-AE3) -> -0.41544772 | AF4: =AE4*(1-AF3) -> -0.41544772 | AG4: =AF4*(1-AG3) -> -0.41544772 | AH4: =AG4*(1-AH3) -> -0.41544772 | AI4: =AH4*(1-AI3) -> -0.41544772 | AJ4: =AI4*(1-AJ3) -> -0.41544772 | AM4: I | AN4: WARNING : VOLUME CHANGE HERE MUST NOT IMPACT THE PACKAGE VOLUME OFFER | AW4: I | AX4: Part impacted by productivity | AY4: =AD4/$AV$7 -> -0.051930965 | AZ4: =AE4/$AV$7 -> -0.051930965 | BA4: =AF4/$AV$7 -> -0.051930965 | BB4: =AG4/$AV$7 -> -0.051930965 | BC4: =AH4/$AV$7 -> -0.051930965 | BD4: =AI4/$AV$7 -> -0.051930965 | BE4: =AJ4/$AV$7 -> -0.051930965
A5: Packaging and transportation | B5: 0.10202582 | C5: 0.10202582 | D5: 0.10202582 | E5: 0.10202582 | F5: 0.10202582 | G5: 0.10202582 | H5: 0.10202582 | S5: I | W5: ='RFQ Data'!C8 -> 0 | X5: ='RFQ Data'!D8 -> RMB | Y5: Customer curenccy | AC5: Packaging and transportation | AD5: =B5 -> 0.10202582 | AE5: =C5 -> 0.10202582 | AF5: =D5 -> 0.10202582 | AG5: =E5 -> 0.10202582 | AH5: =F5 -> 0.10202582 | AI5: =G5 -> 0.10202582 | AJ5: =H5 -> 0.10202582 | AM5: I | AW5: I | AX5: Packaging and transportation | AY5: =AD5/$AV$7 -> 0.012753228 | AZ5: =AE5/$AV$7 -> 0.012753228 | BA5: =AF5/$AV$7 -> 0.012753228 | BB5: =AG5/$AV$7 -> 0.012753228 | BC5: =AH5/$AV$7 -> 0.012753228 | BD5: =AI5/$AV$7 -> 0.012753228 | BE5: =AJ5/$AV$7 -> 0.012753228
A6: Indexed material | B6: 0.31342189 | C6: 0.31342189 | D6: 0.31342189 | E6: 0.31342189 | F6: 0.31342189 | G6: 0.31342189 | H6: 0.31342189 | J6: 2025 | K6: 2026 | L6: 2027 | M6: 2028 | N6: 2029 | O6: 2030 | P6: Max productivity | S6: I | AC6: Indexed material | AD6: =B6 -> 0.31342189 | AE6: =C6 -> 0.31342189 | AF6: =D6 -> 0.31342189 | AG6: =E6 -> 0.31342189 | AH6: =F6 -> 0.31342189 | AI6: =G6 -> 0.31342189 | AJ6: =H6 -> 0.31342189 | AM6: I | AN6: Currency rate of costing | AU6: new currency rate | AW6: I | AX6: Indexed material | AY6: =AD6/$AV$7 -> 0.039177736 | AZ6: =AE6/$AV$7 -> 0.039177736 | BA6: =AF6/$AV$7 -> 0.039177736 | BB6: =AG6/$AV$7 -> 0.039177736 | BC6: =AH6/$AV$7 -> 0.039177736 | BD6: =AI6/$AV$7 -> 0.039177736 | BE6: =AJ6/$AV$7 -> 0.039177736
A7: Final price | B7: 1.3331334 | C7: 1.3331334 | D7: 1.3331334 | E7: 1.3331334 | F7: 1.3331334 | G7: 1.3331334 | H7: 1.3331334 | I7: RMB | J7: 0 | K7: 0 | L7: 0 | M7: 0 | N7: 0 | O7: 0 | S7: I | U7: New PRICE for simulation | X7: =X4 -> RMB | AA7: -----> | AC7: Final price (Sales target) | AD7: =T12 -> 0 | AE7: =+AE4+AE5+AE6 -> 0 | AF7: =+AF4+AF5+AF6 -> 0 | AG7: =+AG4+AG5+AG6 -> 0 | AH7: =+AH4+AH5+AH6 -> 0 | AI7: =+AI4+AI5+AI6 -> 0 | AJ7: =+AJ4+AJ5+AJ6 -> 0 | AK7: =I7 -> RMB | AM7: I | AP7: second currency : | AQ7: =$P$52 -> EUR | AR7: rate : | AS7: ='RFQ Data'!K23 -> 8 | AT7: ='RFQ Data'!J23 -> EURRMB | AV7: =IF(AU7<>0,AU7,AS7) -> 8 | AW7: I | AX7: Final price (Sales target) | AY7: =AD7/$AV$7 -> 0 | AZ7: =AE7/$AV$7 -> 0 | BA7: =AF7/$AV$7 -> 0 | BB7: =AG7/$AV$7 -> 0 | BC7: =AH7/$AV$7 -> 0 | BD7: =AI7/$AV$7 -> 0 | BE7: =AJ7/$AV$7 -> 0 | BF7: =$P$52 -> EUR
A8: Sales (kRMB) | B8: 0 | C8: 666.56668 | D8: 666.56668 | E8: 666.56668 | F8: 666.56668 | G8: 666.56668 | H8: 0 | I8: 666.56668 | S8: I | AC8: =A8 -> Sales (kRMB) | AD8: =+AD7*AD2 -> 0 | AE8: =+AE7*AE2 -> 0 | AF8: =+AF7*AF2 -> 0 | AG8: =+AG7*AG2 -> 0 | AH8: =+AH7*AH2 -> 0 | AI8: =+AI7*AI2 -> 0 | AJ8: =+AJ7*AJ2 -> 0 | AK8: =AE8 -> 0 | AM8: I | AO8: EUR | AP8: RMB | AQ8: USD | AR8: INR | AS8: KWON | AU8: only used for simulation transposition | AW8: I | AX8: =+"Sales (k"&BF7&")" -> Sales (kEUR) | AY8: =AD8/$AV$7 -> 0 | AZ8: =AE8/$AV$7 -> 0 | BA8: =AF8/$AV$7 -> 0 | BB8: =AG8/$AV$7 -> 0 | BC8: =AH8/$AV$7 -> 0 | BD8: =AI8/$AV$7 -> 0 | BE8: =AJ8/$AV$7 -> 0 | BF8: =AZ8 -> 0
S9: I | AM9: I | AO9: ='RFQ Data'!H22 -> 0.125 | AP9: ='RFQ Data'!I22 -> 1 | AQ9: ='RFQ Data'!J22 -> 0.1375 | AR9: ='RFQ Data'!K22 -> 11.875 | AS9: ='RFQ Data'!L22 -> 0.195 | AU9: not take in account in costing | AW9: I
A10: RM incl. supplier productivity | B10: 0 | C10: 213.79154 | D10: 213.79154 | E10: 213.79154 | F10: 213.79154 | G10: 213.79154 | H10: 0 | I10: 213.79154 | S10: I | T10: Simulation at Target Price + Indexation changes + with vol effect at | Z10: =U49 -> 1.151916 | AA10: set up it below | AC10: RM incl. supplier productivity | AD10: =+(AE10+0)/AE$2*AD$2 -> 0 | AE10: =(C10/C$2++SUM(INDEX_IMPACT))*AE$2 -> 213.79154 | AF10: =(D10/D$2++SUM(INDEX_IMPACT))*AF$2 -> 213.79154 | AG10: =(E10/E$2++SUM(INDEX_IMPACT))*AG$2 -> 213.79154 | AH10: =(F10/F$2++SUM(INDEX_IMPACT))*AH$2 -> 213.79154 | AI10: =(G10/G$2++SUM(INDEX_IMPACT))*AI$2 -> 213.79154 | AJ10: =+AI10/AI$2*AJ$2 -> 0 | AK10: =AE10 -> 213.79154 | AM10: I | AU10: not impacted RM cost, … | AW10: I | AX10: RM incl. supplier productivity | AY10: =AD10/$AV$7 -> 0 | AZ10: =AE10/$AV$7 -> 26.723943 | BA10: =AF10/$AV$7 -> 26.723943 | BB10: =AG10/$AV$7 -> 26.723943 | BC10: =AH10/$AV$7 -> 26.723943 | BD10: =AI10/$AV$7 -> 26.723943 | BE10: =AJ10/$AV$7 -> 0 | BF10: =AZ10 -> 26.723943
A11: Packaging | B11: 0 | C11: 1.5223024 | D11: 1.5223024 | E11: 1.5223024 | F11: 1.5223024 | G11: 1.5223024 | H11: 0 | I11: 1.5223024 | S11: I | Z11: =$N$52 -> RMB | AA11: =$P$52 -> EUR | AC11: Packaging | AD11: =AE11/AE2*AD$2 -> 0 | AE11: =C11/C$2*AE$2 -> 1.5223024 | AF11: =D11/D$2*AF$2 -> 1.5223024 | AG11: =E11/E$2*AG$2 -> 1.5223024 | AH11: =F11/F$2*AH$2 -> 1.5223024 | AI11: =G11/G$2*AI$2 -> 1.5223024 | AJ11: =(AI11+0)/AI2*AJ$2 -> 0 | AK11: =AE11 -> 1.5223024 | AM11: I | AW11: I | AX11: Packaging | AY11: =AD11/$AV$7 -> 0 | AZ11: =AE11/$AV$7 -> 0.19028781 | BA11: =AF11/$AV$7 -> 0.19028781 | BB11: =AG11/$AV$7 -> 0.19028781 | BC11: =AH11/$AV$7 -> 0.19028781 | BD11: =AI11/$AV$7 -> 0.19028781 | BE11: =AJ11/$AV$7 -> 0 | BF11: =AZ11 -> 0.19028781
A12: Total Material | B12: 0 | C12: 215.31384 | D12: 215.31384 | E12: 215.31384 | F12: 215.31384 | G12: 215.31384 | H12: 0 | S12: I | T12: =IF(W7<>0,W7,W4) -> 0 | U12: =N52 -> RMB | V12: =Z12/$T$12 -> #DIV/0! | X12: RM + Packaging | Z12: =N43+SUM(INDEX_IMPACT) -> 0.43062769 | AA12: =Z12/$K$52 -> 0.053828461 | AC12: Total Material | AD12: =+AD10+AD11 -> 0 | AE12: =+AE10+AE11 -> 215.31384 | AF12: =+AF10+AF11 -> 215.31384 | AG12: =+AG10+AG11 -> 215.31384 | AH12: =+AH10+AH11 -> 215.31384 | AI12: =+AI10+AI11 -> 215.31384 | AJ12: =+AJ10+AJ11 -> 0 | AM12: I | AW12: I | AX12: Total Material | AY12: =AD12/$AV$7 -> 0 | AZ12: =AE12/$AV$7 -> 26.914231 | BA12: =AF12/$AV$7 -> 26.914231 | BB12: =AG12/$AV$7 -> 26.914231 | BC12: =AH12/$AV$7 -> 26.914231 | BD12: =AI12/$AV$7 -> 26.914231 | BE12: =AJ12/$AV$7 -> 0
B13: 0 | C13: 0.32073542 | D13: 0.32073542 | E13: 0.32073542 | F13: 0.32073542 | G13: 0.32073542 | H13: 0 | S13: I | V13: =(Z13+Z14+Z15)/$T$12 -> #DIV/0! | W13: DC | X13: DL | Z13: =N44 -> 0.060738826 | AA13: =Z13/$K$52 -> 0.0075923533 | AD13: =+IF(AD8<>0,AD10/AD8,0) -> 0 | AE13: =+IF(AE8<>0,AE10/AE8,0) -> 0 | AF13: =+IF(AF8<>0,AF10/AF8,0) -> 0 | AG13: =+IF(AG8<>0,AG10/AG8,0) -> 0 | AH13: =+IF(AH8<>0,AH10/AH8,0) -> 0 | AI13: =+IF(AI8<>0,AI10/AI8,0) -> 0 | AJ13: =+IF(AJ8<>0,AJ10/AJ8,0) -> 0 | AM13: I | AW13: I | AY13: =AD13 -> 0 | AZ13: =AE13 -> 0 | BA13: =AF13 -> 0 | BB13: =AG13 -> 0 | BC13: =AH13 -> 0 | BD13: =AI13 -> 0 | BE13: =AJ13 -> 0
S14: I | T14: =T12/K52 -> 0 | U14: =P52 -> EUR | X14: VOH | Z14: =N45 -> 0.1368822 | AA14: =Z14/$K$52 -> 0.017110275 | AM14: I | AW14: I
A15: DL | B15: 0 | C15: 30.369413 | D15: 30.369413 | E15: 30.369413 | F15: 30.369413 | G15: 30.369413 | H15: 0 | I15: 30.369413 | S15: I | X15: tranportation | Z15: =N46 -> 0.1548453 | AA15: =Z15/$K$52 -> 0.019355663 | AC15: DL | AD15: =+AE15/AE$2*AD$2 -> 0 | AE15: =C15/C$2*AE$2 -> 30.369413 | AF15: =D15/D$2*AF$2 -> 30.369413 | AG15: =E15/E$2*AG$2 -> 30.369413 | AH15: =F15/F$2*AH$2 -> 30.369413 | AI15: =+AH15/AH$2*AI$2 -> 30.369413 | AJ15: =+AI15/AI$2*AJ$2 -> 0 | AK15: =AE15 -> 30.369413 | AM15: I | AW15: I | AX15: DL | AY15: =AD15/$AV$7 -> 0 | AZ15: =AE15/$AV$7 -> 3.7961766 | BA15: =AF15/$AV$7 -> 3.7961766 | BB15: =AG15/$AV$7 -> 3.7961766 | BC15: =AH15/$AV$7 -> 3.7961766 | BD15: =AI15/$AV$7 -> 3.7961766 | BE15: =AJ15/$AV$7 -> 0 | BF15: =AZ15 -> 3.7961766
B16: 0 | C16: 0.045560953 | D16: 0.045560953 | E16: 0.045560953 | F16: 0.045560953 | G16: 0.045560953 | H16: 0 | S16: I | V16: =(Z16+Z17+Z18)/$T$12 -> #DIV/0! | W16: GMDC | X16: FOH + Admin | Z16: =Y47 -> 0.19868335 | AA16: =Z16/$K$52 -> 0.024835419 | AD16: =+IF(AD$8<>0,AD15/AD$8,0) -> 0 | AE16: =+IF(AE$8<>0,AE15/AE$8,0) -> 0 | AF16: =+IF(AF$8<>0,AF15/AF$8,0) -> 0 | AG16: =+IF(AG$8<>0,AG15/AG$8,0) -> 0 | AH16: =+IF(AH$8<>0,AH15/AH$8,0) -> 0 | AI16: =+IF(AI$8<>0,AI15/AI$8,0) -> 0 | AJ16: =+IF(AJ$8<>0,AJ15/AJ$8,0) -> 0 | AM16: I | AW16: I | AY16: =AD16 -> 0 | AZ16: =AE16 -> 0 | BA16: =AF16 -> 0 | BB16: =AG16 -> 0 | BC16: =AH16 -> 0 | BD16: =AI16 -> 0 | BE16: =AJ16 -> 0
A17: VOH | B17: 0 | C17: 68.4411 | D17: 68.4411 | E17: 68.4411 | F17: 68.4411 | G17: 68.4411 | H17: 0 | I17: 68.4411 | S17: I | X17: Fees | Z17: =Y48 -> 0.13113101 | AA17: =Z17/$K$52 -> 0.016391376 | AC17: VOH | AD17: =+AE17/AE$2*AD$2 -> 0 | AE17: =C17/C$2*AE$2 -> 68.4411 | AF17: =D17/D$2*AF$2 -> 68.4411 | AG17: =E17/E$2*AG$2 -> 68.4411 | AH17: =F17/F$2*AH$2 -> 68.4411 | AI17: =+AH17/AH$2*AI$2 -> 68.4411 | AJ17: =+AI17/AI$2*AJ$2 -> 0 | AK17: =AE17 -> 68.4411 | AM17: I | AW17: I | AX17: VOH | AY17: =AD17/$AV$7 -> 0 | AZ17: =AE17/$AV$7 -> 8.5551375 | BA17: =AF17/$AV$7 -> 8.5551375 | BB17: =AG17/$AV$7 -> 8.5551375 | BC17: =AH17/$AV$7 -> 8.5551375 | BD17: =AI17/$AV$7 -> 8.5551375 | BE17: =AJ17/$AV$7 -> 0 | BF17: =AZ17 -> 8.5551375
B18: 0 | C18: 0.10267705 | D18: 0.10267705 | E18: 0.10267705 | F18: 0.10267705 | G18: 0.10267705 | H18: 0 | S18: I | X18: EBITDA | Z18: =T12-SUM(Z12:Z17) -> -1.1129084 | AA18: =Z18/$K$52 -> -0.13911355 | AD18: =+IF(AD$8<>0,AD17/AD$8,0) -> 0 | AE18: =+IF(AE$8<>0,AE17/AE$8,0) -> 0 | AF18: =+IF(AF$8<>0,AF17/AF$8,0) -> 0 | AG18: =+IF(AG$8<>0,AG17/AG$8,0) -> 0 | AH18: =+IF(AH$8<>0,AH17/AH$8,0) -> 0 | AI18: =+IF(AI$8<>0,AI17/AI$8,0) -> 0 | AJ18: =+IF(AJ$8<>0,AJ17/AJ$8,0) -> 0 | AM18: I | AW18: I | AY18: =AD18 -> 0 | AZ18: =AE18 -> 0 | BA18: =AF18 -> 0 | BB18: =AG18 -> 0 | BC18: =AH18 -> 0 | BD18: =AI18 -> 0 | BE18: =AJ18 -> 0
A19: Inbound transportation | B19: 0 | C19: 27.932041 | D19: 27.932041 | E19: 27.932041 | F19: 27.932041 | G19: 27.932041 | H19: 0 | S19: I | AC19: Inbound transportation | AD19: =+AE19/AE$2*AD$2 -> 0 | AE19: =C19/C$2*AE$2 -> 27.932041 | AF19: =D19/D$2*AF$2 -> 27.932041 | AG19: =E19/E$2*AG$2 -> 27.932041 | AH19: =F19/F$2*AH$2 -> 27.932041 | AI19: =+AH19/AH$2*AI$2 -> 27.932041 | AJ19: =+AI19/AI$2*AJ$2 -> 0 | AM19: I | AW19: I | AX19: Inbound transportation | AY19: =AD19/$AV$7 -> 0 | AZ19: =AE19/$AV$7 -> 3.4915052 | BA19: =AF19/$AV$7 -> 3.4915052 | BB19: =AG19/$AV$7 -> 3.4915052 | BC19: =AH19/$AV$7 -> 3.4915052 | BD19: =AI19/$AV$7 -> 3.4915052 | BE19: =AJ19/$AV$7 -> 0
A20: Outbound Transportation | B20: 0 | C20: 49.49061 | D20: 49.49061 | E20: 49.49061 | F20: 49.49061 | G20: 49.49061 | H20: 0 | S20: I | AC20: Outbound Transportation | AD20: =+AE20/AE$2*AD$2 -> 0 | AE20: =C20/C$2*AE$2 -> 49.49061 | AF20: =D20/D$2*AF$2 -> 49.49061 | AG20: =E20/E$2*AG$2 -> 49.49061 | AH20: =F20/F$2*AH$2 -> 49.49061 | AI20: =+AH20/AH$2*AI$2 -> 49.49061 | AJ20: =+AI20/AI$2*AJ$2 -> 0 | AM20: I | AW20: I | AX20: Outbound Transportation | AY20: =AD20/$AV$7 -> 0 | AZ20: =AE20/$AV$7 -> 6.1863262 | BA20: =AF20/$AV$7 -> 6.1863262 | BB20: =AG20/$AV$7 -> 6.1863262 | BC20: =AH20/$AV$7 -> 6.1863262 | BD20: =AI20/$AV$7 -> 6.1863262 | BE20: =AJ20/$AV$7 -> 0
A21: Total transportation | B21: 0 | C21: 77.422651 | D21: 77.422651 | E21: 77.422651 | F21: 77.422651 | G21: 77.422651 | H21: 0 | I21: 77.422651 | S21: I | AC21: Total transportation | AD21: =+AD19+AD20 -> 0 | AE21: =+AE19+AE20 -> 77.422651 | AF21: =+AF19+AF20 -> 77.422651 | AG21: =+AG19+AG20 -> 77.422651 | AH21: =+AH19+AH20 -> 77.422651 | AI21: =+AI19+AI20 -> 77.422651 | AJ21: =+AJ19+AJ20 -> 0 | AK21: =AE21 -> 77.422651 | AM21: I | AW21: I | AX21: Total transportation | AY21: =AD21/$AV$7 -> 0 | AZ21: =AE21/$AV$7 -> 9.6778314 | BA21: =AF21/$AV$7 -> 9.6778314 | BB21: =AG21/$AV$7 -> 9.6778314 | BC21: =AH21/$AV$7 -> 9.6778314 | BD21: =AI21/$AV$7 -> 9.6778314 | BE21: =AJ21/$AV$7 -> 0 | BF21: =AZ21 -> 9.6778314
B22: 0 | C22: 0.1161514 | D22: 0.1161514 | E22: 0.1161514 | F22: 0.1161514 | G22: 0.1161514 | H22: 0 | S22: I | AD22: =+IF(AD$8<>0,AD21/AD$8,0) -> 0 | AE22: =+IF(AE$8<>0,AE21/AE$8,0) -> 0 | AF22: =+IF(AF$8<>0,AF21/AF$8,0) -> 0 | AG22: =+IF(AG$8<>0,AG21/AG$8,0) -> 0 | AH22: =+IF(AH$8<>0,AH21/AH$8,0) -> 0 | AI22: =+IF(AI$8<>0,AI21/AI$8,0) -> 0 | AJ22: =+IF(AJ$8<>0,AJ21/AJ$8,0) -> 0 | AM22: I | AW22: I | AY22: =AD22 -> 0 | AZ22: =AE22 -> 0 | BA22: =AF22 -> 0 | BB22: =AG22 -> 0 | BC22: =AH22 -> 0 | BD22: =AI22 -> 0 | BE22: =AJ22 -> 0
S23: I | AM23: I | AW23: I
A24: GMDC | B24: 0 | C24: 275.01967 | D24: 275.01967 | E24: 275.01967 | F24: 275.01967 | G24: 275.01967 | H24: 0 | I24: 275.01967 | S24: I | AC24: GMDC | AD24: =+AD8-AD10-AD15-AD17-AD21-AD11 -> 0 | AE24: =+AE8-AE10-AE15-AE17-AE21-AE11 -> -391.54701 | AF24: =+AF8-AF10-AF15-AF17-AF21-AF11 -> -391.54701 | AG24: =+AG8-AG10-AG15-AG17-AG21-AG11 -> -391.54701 | AH24: =+AH8-AH10-AH15-AH17-AH21-AH11 -> -391.54701 | AI24: =+AI8-AI10-AI15-AI17-AI21-AI11 -> -391.54701 | AJ24: =+AJ8-AJ10-AJ15-AJ17-AJ21 -> 0 | AK24: =AE24 -> -391.54701 | AM24: I | AW24: I | AX24: GMDC | AY24: =AD24/$AV$7 -> 0 | AZ24: =AE24/$AV$7 -> -48.943376 | BA24: =AF24/$AV$7 -> -48.943376 | BB24: =AG24/$AV$7 -> -48.943376 | BC24: =AH24/$AV$7 -> -48.943376 | BD24: =AI24/$AV$7 -> -48.943376 | BE24: =AJ24/$AV$7 -> 0 | BF24: =AZ24 -> -48.943376
B25: 0 | C25: 0.41259139 | D25: 0.41259139 | E25: 0.41259139 | F25: 0.41259139 | G25: 0.41259139 | H25: 0 | S25: I | AD25: =+IF(AD$8<>0,AD24/AD$8,0) -> 0 | AE25: =+IF(AE$8<>0,AE24/AE$8,0) -> 0 | AF25: =+IF(AF$8<>0,AF24/AF$8,0) -> 0 | AG25: =+IF(AG$8<>0,AG24/AG$8,0) -> 0 | AH25: =+IF(AH$8<>0,AH24/AH$8,0) -> 0 | AI25: =+IF(AI$8<>0,AI24/AI$8,0) -> 0 | AJ25: =+IF(AJ$8<>0,AJ24/AJ$8,0) -> 0 | AM25: I | AW25: I | AY25: =AD25 -> 0 | AZ25: =AE25 -> 0 | BA25: =AF25 -> 0 | BB25: =AG25 -> 0 | BC25: =AH25 -> 0 | BD25: =AI25 -> 0 | BE25: =AJ25 -> 0
S26: I | AM26: I | AW26: I
A27: FOH + Admin | B27: 0 | C27: 99.341675 | D27: 99.341675 | E27: 99.341675 | F27: 99.341675 | G27: 99.341675 | H27: 0 | I27: 99.341675 | S27: I | AC27: FOH + Admin | AD27: =$Z$16*AD$2 -> 0 | AE27: =$Z$16*AE$2 -> 99.341675 | AF27: =$Z$16*AF$2 -> 99.341675 | AG27: =$Z$16*AG$2 -> 99.341675 | AH27: =$Z$16*AH$2 -> 99.341675 | AI27: =$Z$16*AI$2 -> 99.341675 | AJ27: =$Z$16*AJ$2 -> 0 | AK27: =AE27 -> 99.341675 | AM27: I | AW27: I | AX27: FOH + Admin | AY27: =AD27/$AV$7 -> 0 | AZ27: =AE27/$AV$7 -> 12.417709 | BA27: =AF27/$AV$7 -> 12.417709 | BB27: =AG27/$AV$7 -> 12.417709 | BC27: =AH27/$AV$7 -> 12.417709 | BD27: =AI27/$AV$7 -> 12.417709 | BE27: =AJ27/$AV$7 -> 0 | BF27: =AZ27 -> 12.417709
B28: 0 | C28: 0.14903486 | D28: 0.14903486 | E28: 0.14903486 | F28: 0.14903486 | G28: 0.14903486 | H28: 0 | S28: I | AD28: =+IF(AD$8<>0,AD27/AD$8,0) -> 0 | AE28: =+IF(AE$8<>0,AE27/AE$8,0) -> 0 | AF28: =+IF(AF$8<>0,AF27/AF$8,0) -> 0 | AG28: =+IF(AG$8<>0,AG27/AG$8,0) -> 0 | AH28: =+IF(AH$8<>0,AH27/AH$8,0) -> 0 | AI28: =+IF(AI$8<>0,AI27/AI$8,0) -> 0 | AJ28: =+IF(AJ$8<>0,AJ27/AJ$8,0) -> 0 | AM28: I | AW28: I | AY28: =AD28 -> 0 | AZ28: =AE28 -> 0 | BA28: =AF28 -> 0 | BB28: =AG28 -> 0 | BC28: =AH28 -> 0 | BD28: =AI28 -> 0 | BE28: =AJ28 -> 0
A29: Fees | B29: 0 | C29: 65.565505 | D29: 65.565505 | E29: 65.565505 | F29: 65.565505 | G29: 65.565505 | H29: 0 | I29: 65.565505 | S29: I | AC29: Fees | AD29: =$Z$17*AD$2 -> 0 | AE29: =$Z$17*AE$2 -> 65.565505 | AF29: =$Z$17*AF$2 -> 65.565505 | AG29: =$Z$17*AG$2 -> 65.565505 | AH29: =$Z$17*AH$2 -> 65.565505 | AI29: =$Z$17*AI$2 -> 65.565505 | AJ29: =$Z$17*AJ$2 -> 0 | AK29: =AE29 -> 65.565505 | AM29: I | AW29: I | AX29: Fees | AY29: 0.0290778 | AZ29: 0.0290778 | BA29: 0.0290778 | BB29: 0.0290778 | BC29: 0.0290778 | BD29: 0.0290778 | BE29: 0.0290778 | BF29: =AZ29 -> 0.0290778
B30: 0 | C30: 0.09836301 | D30: 0.09836301 | E30: 0.09836301 | F30: 0.09836301 | G30: 0.09836301 | H30: 0 | S30: I | AD30: =+IF(AD$8<>0,AD29/AD$8,0) -> 0 | AE30: =+IF(AE$8<>0,AE29/AE$8,0) -> 0 | AF30: =+IF(AF$8<>0,AF29/AF$8,0) -> 0 | AG30: =+IF(AG$8<>0,AG29/AG$8,0) -> 0 | AH30: =+IF(AH$8<>0,AH29/AH$8,0) -> 0 | AI30: =+IF(AI$8<>0,AI29/AI$8,0) -> 0 | AJ30: =+IF(AJ$8<>0,AJ29/AJ$8,0) -> 0 | AM30: I | AW30: I | AY30: =AD30 -> 0 | AZ30: =AE30 -> 0 | BA30: =AF30 -> 0 | BB30: =AG30 -> 0 | BC30: =AH30 -> 0 | BD30: =AI30 -> 0 | BE30: =AJ30 -> 0
S31: I | AM31: I | AW31: I
A32: EBITDA | B32: 0 | C32: 110.11249 | D32: 110.11249 | E32: 110.11249 | F32: 110.11249 | G32: 110.11249 | H32: 0 | I32: 110.11249 | S32: I | AC32: EBITDA | AD32: =+AD24-AD27-AD29 -> 0 | AE32: =+AE24-AE27-AE29 -> -556.45419 | AF32: =+AF24-AF27-AF29 -> -556.45419 | AG32: =+AG24-AG27-AG29 -> -556.45419 | AH32: =+AH24-AH27-AH29 -> -556.45419 | AI32: =+AI24-AI27-AI29 -> -556.45419 | AJ32: =+AJ24-AJ27-AJ29 -> 0 | AK32: =AE32 -> -556.45419 | AM32: I | AW32: I | AX32: EBITDA | AY32: =AD32/$AV$7 -> 0 | AZ32: =AE32/$AV$7 -> -69.556774 | BA32: =AF32/$AV$7 -> -69.556774 | BB32: =AG32/$AV$7 -> -69.556774 | BC32: =AH32/$AV$7 -> -69.556774 | BD32: =AI32/$AV$7 -> -69.556774 | BE32: =AJ32/$AV$7 -> 0 | BF32: =AZ32 -> -69.556774
B33: 0 | C33: 0.16519352 | D33: 0.16519352 | E33: 0.16519352 | F33: 0.16519352 | G33: 0.16519352 | H33: 0 | S33: I | AD33: =+IF(AD$8<>0,AD32/AD$8,0) -> 0 | AE33: =+IF(AE$8<>0,AE32/AE$8,0) -> 0 | AF33: =+IF(AF$8<>0,AF32/AF$8,0) -> 0 | AG33: =+IF(AG$8<>0,AG32/AG$8,0) -> 0 | AH33: =+IF(AH$8<>0,AH32/AH$8,0) -> 0 | AI33: =+IF(AI$8<>0,AI32/AI$8,0) -> 0 | AJ33: =+IF(AJ$8<>0,AJ32/AJ$8,0) -> 0 | AM33: I | AW33: I | AY33: =AD33 -> 0 | AZ33: =AE33 -> 0 | BA33: =AF33 -> 0 | BB33: =AG33 -> 0 | BC33: =AH33 -> 0 | BD33: =AI33 -> 0 | BE33: =AJ33 -> 0
S34: I | AM34: I | AW34: I
A35: Depreciation | B35: 0 | C35: 15.985764 | D35: 15.985764 | E35: 15.985764 | F35: 15.985764 | G35: 15.985764 | H35: 0 | I35: 15.985764 | S35: I | AC35: Depreciation | AD35: =+AD66 -> 0 | AE35: =+AE66 -> 15.985764 | AF35: =+AF66 -> 15.985764 | AG35: =+AG66 -> 15.985764 | AH35: =+AH66 -> 15.985764 | AI35: =+AI66 -> 15.985764 | AJ35: =+AJ66 -> 0 | AK35: =AE35 -> 15.985764 | AM35: I | AW35: I | AX35: Depreciation | AY35: =AD35/$AV$7 -> 0 | AZ35: =AE35/$AV$7 -> 1.9982204 | BA35: =AF35/$AV$7 -> 1.9982204 | BB35: =AG35/$AV$7 -> 1.9982204 | BC35: =AH35/$AV$7 -> 1.9982204 | BD35: =AI35/$AV$7 -> 1.9982204 | BE35: =AJ35/$AV$7 -> 0 | BF35: =AZ35 -> 1.9982204
A36: Financial cost | B36: 0 | C36: 0.1 | D36: 15.170731 | E36: 9.9065372 | F36: 4.3659736 | G36: -1.4654695 | H36: -7.6030634 | I36: 0.1 | S36: I | AC36: Financial cost | AD36: =-AD51 -> 0 | AE36: =-AE51 -> #DIV/0! | AF36: =-AF51 -> #DIV/0! | AG36: =-AG51 -> #DIV/0! | AH36: =-AH51 -> #DIV/0! | AI36: =-AI51 -> #DIV/0! | AJ36: =-AJ51 -> #DIV/0! | AK36: =AE36 -> #DIV/0! | AM36: I | AW36: I | AX36: Financial cost | AY36: =AD36/$AV$7 -> 0 | AZ36: =AE36/$AV$7 -> #DIV/0! | BA36: =AF36/$AV$7 -> #DIV/0! | BB36: =AG36/$AV$7 -> #DIV/0! | BC36: =AH36/$AV$7 -> #DIV/0! | BD36: =AI36/$AV$7 -> #DIV/0! | BE36: =AJ36/$AV$7 -> #DIV/0! | BF36: =AZ36 -> #DIV/0!
K37: Parameter box | M37: 1.4379586 | S37: I | W37: min price / max vol (without silver): | X37: =M37 -> 1.4379586 | AM37: I | AW37: I
A38: Operation Income | B38: 0 | C38: 94.02673 | D38: 78.955999 | E38: 84.220193 | F38: 89.760756 | G38: 95.5922 | H38: 7.6030634 | I38: 94.02673 | S38: I | AC38: Operatin Income | AD38: =+AD32-AD35-AD36 -> 0 | AE38: =+AE32-AE35-AE36 -> #DIV/0! | AF38: =+AF32-AF35-AF36 -> #DIV/0! | AG38: =+AG32-AG35-AG36 -> #DIV/0! | AH38: =+AH32-AH35-AH36 -> #DIV/0! | AI38: =+AI32-AI35-AI36 -> #DIV/0! | AJ38: =+AJ32-AJ35-AJ36 -> #DIV/0! | AK38: =AE38 -> #DIV/0! | AM38: I | AW38: I | AX38: Operatin Income | AY38: =AD38/$AV$7 -> 0 | AZ38: =AE38/$AV$7 -> #DIV/0! | BA38: =AF38/$AV$7 -> #DIV/0! | BB38: =AG38/$AV$7 -> #DIV/0! | BC38: =AH38/$AV$7 -> #DIV/0! | BD38: =AI38/$AV$7 -> #DIV/0! | BE38: =AJ38/$AV$7 -> #DIV/0! | BF38: =AZ38 -> #DIV/0!
B39: 0 | C39: 0.14106125 | D39: 0.11845176 | E39: 0.12634924 | F39: 0.13466133 | G39: 0.14340981 | H39: 0 | S39: I | AD39: =+IF(AD$8<>0,AD38/AD$8,0) -> 0 | AE39: =+IF(AE$8<>0,AE38/AE$8,0) -> 0 | AF39: =+IF(AF$8<>0,AF38/AF$8,0) -> 0 | AG39: =+IF(AG$8<>0,AG38/AG$8,0) -> 0 | AH39: =+IF(AH$8<>0,AH38/AH$8,0) -> 0 | AI39: =+IF(AI$8<>0,AI38/AI$8,0) -> 0 | AJ39: =+IF(AJ$8<>0,AJ38/AJ$8,0) -> 0 | AM39: I | AW39: I | AY39: =AD39 -> 0 | AZ39: =AE39 -> 0 | BA39: =AF39 -> 0 | BB39: =AG39 -> 0 | BC39: =AH39 -> 0 | BD39: =AI39 -> 0 | BE39: =AJ39 -> 0
K40: Initial SCENARIO for a package volume of : | O40: 500 | P40: Kparts | S40: I | T40: LOOK FOR PACKAGE OFFER or ANOTHER SCENARIO | AA40: to be validated with VP Sales | AM40: I | AW40: I
A41: Taxes | B41: 0 | C41: 23.506683 | D41: 19.739 | E41: 21.055048 | F41: 22.440189 | G41: 23.89805 | H41: 1.9007659 | I41: 23.506683 | N41: /unit | O41: /year | P41: /unit | Q41: /year | S41: I | X41: and adjust global volume | Z41: Kparts/y | AC41: Taxes | AD41: =B41/B$38*AD$38 -> #DIV/0! | AE41: =C41/C$38*AE$38 -> #DIV/0! | AF41: =D41/D$38*AF$38 -> #DIV/0! | AG41: =E41/E$38*AG$38 -> #DIV/0! | AH41: =F41/F$38*AH$38 -> #DIV/0! | AI41: =G41/G$38*AI$38 -> #DIV/0! | AJ41: =H41/H$38*AJ$38 -> #DIV/0! | AK41: =AE41 -> #DIV/0! | AM41: I | AW41: I | AX41: Taxes | AY41: =AD41/$AV$7 -> #DIV/0! | AZ41: =AE41/$AV$7 -> #DIV/0! | BA41: =AF41/$AV$7 -> #DIV/0! | BB41: =AG41/$AV$7 -> #DIV/0! | BC41: =AH41/$AV$7 -> #DIV/0! | BD41: =AI41/$AV$7 -> #DIV/0! | BE41: =AJ41/$AV$7 -> #DIV/0! | BF41: =AZ41 -> #DIV/0!
S42: I | AM42: I | AW42: I
A43: Net result | B43: 0 | C43: 70.520048 | D43: 59.217 | E43: 63.165145 | F43: 67.320567 | G43: 71.69415 | H43: 5.7022976 | I43: 70.520048 | J43: 0.32301921 | L43: RM + Packaging | N43: 0.43062769 | O43: 215.31384 | P43: 0.053828461 | Q43: 26.914231 | S43: I | T43: =Q50/AVERAGE('RFQ Data'!D13:H13)*SIMUL_VOL -> 0 | U43: Keur | W43: RM + Packaging | Y43: =N43 -> 0.43062769 | Z43: =Y43/$K$52 -> 0.053828461 | AC43: Net result | AD43: =+AD38-AD41 -> #DIV/0! | AE43: =+AE38-AE41 -> #DIV/0! | AF43: =+AF38-AF41 -> #DIV/0! | AG43: =+AG38-AG41 -> #DIV/0! | AH43: =+AH38-AH41 -> #DIV/0! | AI43: =+AI38-AI41 -> #DIV/0! | AJ43: =+AJ38-AJ41 -> #DIV/0! | AK43: =AE43 -> #DIV/0! | AM43: I | AW43: I | AX43: Net result | AY43: =+AY38-AY41 -> #DIV/0! | AZ43: =+AZ38-AZ41 -> #DIV/0! | BA43: =+BA38-BA41 -> #DIV/0! | BB43: =+BB38-BB41 -> #DIV/0! | BC43: =+BC38-BC41 -> #DIV/0! | BD43: =+BD38-BD41 -> #DIV/0! | BE43: =+BE38-BE41 -> #DIV/0! | BF43: =AZ43 -> #DIV/0!
B44: 0 | C44: 0.10579594 | D44: 0.088838823 | E44: 0.094761929 | F44: 0.100996 | G44: 0.10755736 | H44: 0 | K44: DC | L44: DL | N44: 0.060738826 | O44: 30.369413 | P44: 0.0075923533 | Q44: 3.7961766 | S44: I | V44: DC | W44: DL | Y44: =N44 -> 0.060738826 | Z44: =Y44/$K$52 -> 0.0075923533 | AD44: =+IF(AD$8<>0,AD43/AD$8,0) -> 0 | AE44: =+IF(AE$8<>0,AE43/AE$8,0) -> 0 | AF44: =+IF(AF$8<>0,AF43/AF$8,0) -> 0 | AG44: =+IF(AG$8<>0,AG43/AG$8,0) -> 0 | AH44: =+IF(AH$8<>0,AH43/AH$8,0) -> 0 | AI44: =+IF(AI$8<>0,AI43/AI$8,0) -> 0 | AJ44: =+IF(AJ$8<>0,AJ43/AJ$8,0) -> 0 | AM44: I | AW44: I | AY44: =AD44 -> 0 | AZ44: =AE44 -> 0 | BA44: =AF44 -> 0 | BB44: =AG44 -> 0 | BC44: =AH44 -> 0 | BD44: =AI44 -> 0 | BE44: =AJ44 -> 0
J45: 0.2643894 | L45: VOH | N45: 0.1368822 | O45: 68.4411 | P45: 0.017110275 | Q45: 8.5551375 | S45: I | W45: VOH | Y45: =N45 -> 0.1368822 | Z45: =Y45/$K$52 -> 0.017110275 | AM45: I | AW45: I
B46: 2025 | C46: 2026 | D46: 2027 | E46: 2028 | F46: 2029 | G46: 2030 | H46: 2031 | L46: Tranportation & Taxes | N46: 0.1548453 | O46: 77.422651 | P46: 0.019355663 | Q46: 9.6778314 | S46: I | W46: tranportation | Y46: =N46 -> 0.1548453 | Z46: =Y46/$K$52 -> 0.019355663 | AD46: 2023 | AE46: 2024 | AF46: 2025 | AG46: 2026 | AH46: 2027 | AI46: 2028 | AJ46: 2029 | AM46: I | AW46: I | AY46: 2023 | AZ46: 2024 | BA46: 2025 | BB46: 2026 | BC46: 2027 | BD46: 2028 | BE46: 2029
A47: EBITDA | B47: 0 | C47: 110.11249 | D47: 110.11249 | E47: 110.11249 | F47: 110.11249 | G47: 110.11249 | H47: 0 | K47: GMDC | L47: FOH + Admin | N47: 0.19868335 | O47: 99.341675 | P47: 0.024835419 | Q47: 12.417709 | S47: I | U47: New | V47: GMDC | W47: FOH + Admin | Y47: =N47/$V$60*$U$49 -> 0.19868335 | Z47: =Y47/$K$52 -> 0.024835419 | AC47: EBITDA | AD47: =+AE47/AE$2*AD$2 -> 0 | AE47: =C47/C$2*AE$2 -> 110.11249 | AF47: =D47/D$2*AF$2 -> 110.11249 | AG47: =E47/E$2*AG$2 -> 110.11249 | AH47: =F47/F$2*AH$2 -> 110.11249 | AI47: =+AH47/AH$2*AI$2 -> 110.11249 | AJ47: =+AI47/AI$2*AJ$2 -> 0 | AM47: I | AW47: I | AX47: EBITDA | AY47: =AD47/$AV$7 -> 0 | AZ47: =AE47/$AV$7 -> 13.764062 | BA47: =AF47/$AV$7 -> 13.764062 | BB47: =AG47/$AV$7 -> 13.764062 | BC47: =AH47/$AV$7 -> 13.764062 | BD47: =AI47/$AV$7 -> 13.764062 | BE47: =AJ47/$AV$7 -> 0
A48: Company tax | B48: 0 | C48: -23.506683 | D48: -19.739 | E48: -21.055048 | F48: -22.440189 | G48: -23.89805 | H48: -1.9007659 | J48: 0.41259139 | L48: Fees | N48: 0.13113101 | O48: 65.565505 | P48: 0.016391376 | Q48: 8.1956882 | S48: I | U48: vol effect | W48: Fees | Y48: =N48/$V$60*$U$49 -> 0.13113101 | Z48: =Y48/$K$52 -> 0.016391376 | AC48: Company tax | AD48: =-AD41 -> #DIV/0! | AE48: =-AE41 -> #DIV/0! | AF48: =-AF41 -> #DIV/0! | AG48: =-AG41 -> #DIV/0! | AH48: =-AH41 -> #DIV/0! | AI48: =-AI41 -> #DIV/0! | AJ48: =-AJ41 -> #DIV/0! | AM48: I | AW48: I | AX48: Company tax | AY48: =AD48/$AV$7 -> #DIV/0! | AZ48: =AE48/$AV$7 -> #DIV/0! | BA48: =AF48/$AV$7 -> #DIV/0! | BB48: =AG48/$AV$7 -> #DIV/0! | BC48: =AH48/$AV$7 -> #DIV/0! | BD48: =AI48/$AV$7 -> #DIV/0! | BE48: =AJ48/$AV$7 -> #DIV/0!
A49: CAPEX | B49: 0 | C49: -79.928818 | D49: 0 | E49: 0 | F49: 0 | G49: 0 | H49: 0 | L49: EBITDA | N49: 0.22022499 | O49: 110.11249 | P49: 0.027528123 | Q49: 13.764062 | S49: I | U49: =(V$56/$V$57*$I$2/IF(Y$41<>0,$Y$41,$I$2)/$Y$57)^$Y$56/$V$58*V60 -> 1.151916 | W49: EBITDA | Y49: =N49 -> 0.22022499 | Z49: =Y49/$K$52 -> 0.027528123 | AC49: CAPEX | AD49: =-AD60 -> 0 | AE49: =-AE60 -> -79.928818 | AF49: =-AF60 -> 0 | AG49: =-AG60 -> 0 | AH49: =-AH60 -> 0 | AI49: =-AI60 -> 0 | AJ49: =-AJ60 -> 0 | AM49: I | AW49: I | AX49: CAPEX | AY49: =AD49/$AV$7 -> 0 | AZ49: =AE49/$AV$7 -> -9.9911022 | BA49: =AF49/$AV$7 -> 0 | BB49: =AG49/$AV$7 -> 0 | BC49: =AH49/$AV$7 -> 0 | BD49: =AI49/$AV$7 -> 0 | BE49: =AJ49/$AV$7 -> 0
A50: DTWC | B50: 0 | C50: -157.2843 | D50: 0 | E50: 0 | F50: 0 | G50: 0 | H50: 157.2843 | L50: T/0 | O50: 666.56668 | Q50: 83.320835 | S50: I | Y50: =$N$52 -> RMB | Z50: =$P$52 -> EUR | AC50: DTWC | AD50: =+AD75 -> 0 | AE50: =+AE75 -> -157.2843 | AF50: =+AF75 -> 0 | AG50: =+AG75 -> 0 | AH50: =+AH75 -> 0 | AI50: =+AI75 -> 0 | AJ50: =+AJ75 -> 157.2843 | AM50: I | AW50: I | AX50: DTWC | AY50: =AD50/$AV$7 -> 0 | AZ50: =AE50/$AV$7 -> -19.660537 | BA50: =AF50/$AV$7 -> 0 | BB50: =AG50/$AV$7 -> 0 | BC50: =AH50/$AV$7 -> 0 | BD50: =AI50/$AV$7 -> 0 | BE50: =AJ50/$AV$7 -> 19.660537
A51: Financial cost | B51: 0 | C51: -0.1 | D51: -15.170731 | E51: -9.9065372 | F51: -4.3659736 | G51: 1.4654695 | H51: 7.6030634 | K51: EURRMB | L51: Min Price | N51: 1.3331334 | O51: 1st Cur | P51: 0.16664167 | Q51: 2nd Cur | S51: I | X51: Proposed price | Y51: =SUM(Y43:Y49) -> 1.3331334 | Z51: =SUM(Z43:Z49) -> 0.16664167 | AC51: Financial cost | AD51: =+IF((AD47+AD49+AD50)*1.1*0.1<0,(AD47+AD49+AD50)*1.1*0.1,0) -> 0 | AE51: =10%*AD54 -> #DIV/0! | AF51: =10%*AE54 -> #DIV/0! | AG51: =10%*AF54 -> #DIV/0! | AH51: =10%*AG54 -> #DIV/0! | AI51: =10%*AH54 -> #DIV/0! | AJ51: =10%*AI54 -> #DIV/0! | AM51: I | AW51: I | AX51: Financial cost | AY51: =AD51/$AV$7 -> 0 | AZ51: =AE51/$AV$7 -> #DIV/0! | BA51: =AF51/$AV$7 -> #DIV/0! | BB51: =AG51/$AV$7 -> #DIV/0! | BC51: =AH51/$AV$7 -> #DIV/0! | BD51: =AI51/$AV$7 -> #DIV/0! | BE51: =AJ51/$AV$7 -> #DIV/0!
A52: Tax on dividend | B52: 0 | C52: 0 | D52: -22.560829 | E52: -23.745272 | F52: -24.991899 | G52: -26.303974 | H52: -48.895979 | K52: 8 | N52: RMB | O52: RMB | P52: EUR | Q52: EUR | S52: I | Y52: for exact calculation on 1 part#, request a new costing by changing the Package vol on a RFQ scenario | AC52: Tax on dividend | AD52: =IF(SUM(B47:B51)>0,B52/SUM(B47:B51)*SUM(AD47:AD51),0) -> 0 | AE52: =IF(SUM(C47:C51)>0,C52/SUM(C47:C51)*SUM(AE47:AE51),0) -> 0 | AF52: =IF(SUM(D47:D51)>0,D52/SUM(D47:D51)*SUM(AF47:AF51),0) -> #DIV/0! | AG52: =IF(SUM(E47:E51)>0,E52/SUM(E47:E51)*SUM(AG47:AG51),0) -> #DIV/0! | AH52: =IF(SUM(F47:F51)>0,F52/SUM(F47:F51)*SUM(AH47:AH51),0) -> #DIV/0! | AI52: =IF(SUM(G47:G51)>0,G52/SUM(G47:G51)*SUM(AI47:AI51),0) -> #DIV/0! | AJ52: =IF(SUM(H47:H51)>0,H52/SUM(H47:H51)*SUM(AJ47:AJ51),0) -> #DIV/0! | AM52: I | AW52: I | AX52: Tax on dividend | AY52: =AD52/$AV$7 -> 0 | AZ52: =AE52/$AV$7 -> 0 | BA52: =AF52/$AV$7 -> #DIV/0! | BB52: =AG52/$AV$7 -> #DIV/0! | BC52: =AH52/$AV$7 -> #DIV/0! | BD52: =AI52/$AV$7 -> #DIV/0! | BE52: =AJ52/$AV$7 -> #DIV/0!
A53: Cash | B53: -1 | C53: -150.70731 | D53: 52.641934 | E53: 55.405636 | F53: 58.314432 | G53: 61.375939 | H53: 114.09062 | J53: - | M53: MOQ | N53: 13000 | O53: parts should be produced | S53: I | AC53: Cash | AD53: =+IF(SUM(AD47:AD52)>=0,-1,SUM(AD47:AD52)) -> #DIV/0! | AE53: =+SUM(AE47:AE52) -> #DIV/0! | AF53: =+SUM(AF47:AF52) -> #DIV/0! | AG53: =+SUM(AG47:AG52) -> #DIV/0! | AH53: =+SUM(AH47:AH52) -> #DIV/0! | AI53: =+SUM(AI47:AI52) -> #DIV/0! | AJ53: =+SUM(AJ47:AJ52) -> #DIV/0! | AM53: I | AW53: I | AX53: Cash | AY53: =AD53/$AV$7 -> #DIV/0! | AZ53: =AE53/$AV$7 -> #DIV/0! | BA53: =AF53/$AV$7 -> #DIV/0! | BB53: =AG53/$AV$7 -> #DIV/0! | BC53: =AH53/$AV$7 -> #DIV/0! | BD53: =AI53/$AV$7 -> #DIV/0! | BE53: =AJ53/$AV$7 -> #DIV/0!
A54: Cum cash | B54: -1 | C54: -151.70731 | D54: -99.065372 | E54: -43.659736 | F54: 14.654695 | G54: 76.030634 | H54: 190.12125 | J54: For | K54: Brushes - B-Alt & Auxilairy / t or a | N54: a | O54: Normal | P54: stategy is applicable | S54: I | T54: FOH & FEES CALCULATION | AC54: Cum cash | AD54: =+AD53 -> #DIV/0! | AE54: =+AD54+AE53 -> #DIV/0! | AF54: =+AE54+AF53 -> #DIV/0! | AG54: =+AF54+AG53 -> #DIV/0! | AH54: =+AG54+AH53 -> #DIV/0! | AI54: =+AH54+AI53 -> #DIV/0! | AJ54: =+AI54+AJ53 -> #DIV/0! | AM54: I | AW54: I | AX54: Cum cash | AY54: =AD54/$AV$7 -> #DIV/0! | AZ54: =AE54/$AV$7 -> #DIV/0! | BA54: =AF54/$AV$7 -> #DIV/0! | BB54: =AG54/$AV$7 -> #DIV/0! | BC54: =AH54/$AV$7 -> #DIV/0! | BD54: =AI54/$AV$7 -> #DIV/0! | BE54: =AJ54/$AV$7 -> #DIV/0!
A55: Price | B55: 1.3331334 | C55: RMB | N55: volume effect on FOH&Fees is corresponding to | O55: 1.151916 | S55: I | U55: Volume référecne | V55: 1200 | W55: Kpart | Y55: volume effect parameter | AC55: Price | AD55: =AD7 -> 0 | AE55: EUR | AM55: I | AW55: I | AX55: Price | AY55: =AD55/$AV$7 -> 0 | AZ55: =BF7 -> EUR
A56: ROI | B56: 0.30009445 | N56: With the package volume, vol effect is now at | O56: 1.151916 | S56: I | U56: T/0 reference | V56: 120 | W56: KE | Y56: 0.3 | Z56: amplitude | AC56: ROI | AD56: =B56 -> 0.30009445 | AM56: I | AW56: I | AX56: ROI | AY56: =AD56 -> 0.30009445
A57: NPV (20%) | B57: 0.018335211 | C57: RMB | N57: but maybe, we take a strategic* decision at | S57: I | U57: pseudoT/O of the quote | V57: =AVERAGE('RFQ Data'!C13:H13)*X37/'RFQ Data'!K24 -> 74.893678 | W57: Keur | X57: EURINR | Y57: 1 | Z57: centrage /vol ref | AC57: NPV (20%) | AD57: =B57 -> 0.018335211 | AE57: EUR | AM57: I | AW57: I | AX57: NPV (20%) | AY57: =AD57/$AV$7 -> 0.0022919014 | AZ57: =AZ55 -> EUR
A58: WARNING: Integrates margin on Tooling solt to customer and potential supplier business link | L58: The current decision is in between | N58: Normal | O58: & | P58: little agressive | S58: I | U58: Volume effect | V58: =($V$56/V57/$Y$57)^$Y$56 -> 1.151916 | W58: with normal stategy | AC58: WARNING: Integrates margin on Tooling solt to customer and potential supplier business link | AM58: I | AW58: I | AX58: WARNING: Integrates margin on Tooling solt to customer and potential supplier business link
A59: V V V | B59: 2025 | C59: 2026 | D59: 2027 | E59: 2028 | F59: 2029 | G59: 2030 | H59: 2031 | S59: I | U59: pseudo T/O of the package | V59: =V57/I2*O40 -> 74.893678 | W59: Keur | AC59: V V V | AD59: 2023 | AE59: 2024 | AF59: 2025 | AG59: 2026 | AH59: 2027 | AI59: 2028 | AJ59: 2029 | AM59: I | AW59: I | AX59: V V V | AY59: 2023 | AZ59: 2024 | BA59: 2025 | BB59: 2026 | BC59: 2027 | BD59: 2028 | BE59: 2029
A60: AVOCAPEX +TOOL | B60: 0 | C60: 79.928818 | D60: 0 | E60: 0 | F60: 0 | G60: 0 | H60: 0 | J60: TRANSPORTATION COST | M60: plant# | S60: I | U60: Vol effect selected on RFQ | V60: =IF(O57<>0,O57,O56) -> 1.151916 | AC60: AVOCAPEX +TOOL | AD60: =B60/$I$2*$AU$2 -> 0 | AE60: =C60/$I$2*$AU$2 -> 79.928818 | AF60: =D60/$I$2*$AU$2 -> 0 | AG60: =E60/$I$2*$AU$2 -> 0 | AH60: =F60/$I$2*$AU$2 -> 0 | AI60: =G60/$I$2*$AU$2 -> 0 | AJ60: =H60/$I$2*$AU$2 -> 0 | AM60: I | AW60: I | AX60: AVOCAPEX +TOOL | AY60: =AD60/$AV$7 -> 0 | AZ60: =AE60/$AV$7 -> 9.9911022 | BA60: =AF60/$AV$7 -> 0 | BB60: =AG60/$AV$7 -> 0 | BC60: =AH60/$AV$7 -> 0 | BD60: =AI60/$AV$7 -> 0 | BE60: =AJ60/$AV$7 -> 0
A61: Depreciation Y1 | B61: 0 | C61: 0 | D61: 0 | E61: 0 | F61: 0 | K61: from | L61: Tianjin | M61: 10 | N61: RMB /p | O61: RMB /pallet | P61: EUR /p | Q61: EUR /pallet | S61: I | AC61: Depreciation Y1 | AD61: =B61/$I$2*$AU$2 -> 0 | AE61: =C61/$I$2*$AU$2 -> 0 | AF61: =D61/$I$2*$AU$2 -> 0 | AG61: =E61/$I$2*$AU$2 -> 0 | AH61: =F61/$I$2*$AU$2 -> 0 | AI61: =G61/$I$2*$AU$2 -> 0 | AJ61: =H61/$I$2*$AU$2 -> 0 | AM61: I | AW61: I | AX61: Depreciation Y1 | AY61: =AD61/$AV$7 -> 0 | AZ61: =AE61/$AV$7 -> 0 | BA61: =AF61/$AV$7 -> 0 | BB61: =AG61/$AV$7 -> 0 | BC61: =AH61/$AV$7 -> 0 | BD61: =AI61/$AV$7 -> 0 | BE61: =AJ61/$AV$7 -> 0
A62: Depreciation Y2 | C62: 15.985764 | D62: 15.985764 | E62: 15.985764 | F62: 15.985764 | G62: 15.985764 | K62: to | L62: ElFahs | M62: 5 | N62: 0.14689565 | O62: 4918.5241 | P62: 0.018361957 | Q62: 614.81552 | S62: I | T62: CESSION PRICE & MARGIN BALANCING (GROUP FINANCIAL DECISION) | AC62: Depreciation Y2 | AD62: =B62/$I$2*$AU$2 -> 0 | AE62: =C62/$I$2*$AU$2 -> 15.985764 | AF62: =D62/$I$2*$AU$2 -> 15.985764 | AG62: =E62/$I$2*$AU$2 -> 15.985764 | AH62: =F62/$I$2*$AU$2 -> 15.985764 | AI62: =G62/$I$2*$AU$2 -> 15.985764 | AJ62: =H62/$I$2*$AU$2 -> 0 | AM62: I | AW62: I | AX62: Depreciation Y2 | AY62: =AD62/$AV$7 -> 0 | AZ62: =AE62/$AV$7 -> 1.9982204 | BA62: =AF62/$AV$7 -> 1.9982204 | BB62: =AG62/$AV$7 -> 1.9982204 | BC62: =AH62/$AV$7 -> 1.9982204 | BD62: =AI62/$AV$7 -> 1.9982204 | BE62: =AJ62/$AV$7 -> 0
A63: Depreciation Y3 | D63: 0 | E63: 0 | F63: 0 | G63: 0 | H63: 0 | K63: to | L63: Monterrey | M63: 1 | N63: 0.1335415 | O63: 4471.3856 | P63: 0.016692688 | Q63: 558.9232 | S63: I | T63: 2 | U63: coeff variation on mixes | Y63: (200% default) | AC63: Depreciation Y3 | AD63: =B63/$I$2*$AU$2 -> 0 | AE63: =C63/$I$2*$AU$2 -> 0 | AF63: =D63/$I$2*$AU$2 -> 0 | AG63: =E63/$I$2*$AU$2 -> 0 | AH63: =F63/$I$2*$AU$2 -> 0 | AI63: =G63/$I$2*$AU$2 -> 0 | AJ63: =H63/$I$2*$AU$2 -> 0 | AM63: I | AW63: I | AX63: Depreciation Y3 | AY63: =AD63/$AV$7 -> 0 | AZ63: =AE63/$AV$7 -> 0 | BA63: =AF63/$AV$7 -> 0 | BB63: =AG63/$AV$7 -> 0 | BC63: =AH63/$AV$7 -> 0 | BD63: =AI63/$AV$7 -> 0 | BE63: =AJ63/$AV$7 -> 0
A64: Depreciation Y4 | E64: 0 | F64: 0 | G64: 0 | H64: 0 | I64: 0 | K64: to | L64: Kunshan | M64: 8 | N64: 0.01068332 | O64: 357.71085 | P64: 0.001335415 | Q64: 44.713856 | S64: I | T64: 1 | U64: coeff variation on semi-finished products (blocks) | Y64: (100% default) | AC64: Depreciation Y4 | AD64: =B64/$I$2*$AU$2 -> 0 | AE64: =C64/$I$2*$AU$2 -> 0 | AF64: =D64/$I$2*$AU$2 -> 0 | AG64: =E64/$I$2*$AU$2 -> 0 | AH64: =F64/$I$2*$AU$2 -> 0 | AI64: =G64/$I$2*$AU$2 -> 0 | AJ64: =H64/$I$2*$AU$2 -> 0 | AK64: =I64/$I$2*$AU$2 -> 0 | AM64: I | AW64: I | AX64: Depreciation Y4 | AY64: =AD64/$AV$7 -> 0 | AZ64: =AE64/$AV$7 -> 0 | BA64: =AF64/$AV$7 -> 0 | BB64: =AG64/$AV$7 -> 0 | BC64: =AH64/$AV$7 -> 0 | BD64: =AI64/$AV$7 -> 0 | BE64: =AJ64/$AV$7 -> 0 | BF64: =AK64/$AV$7 -> 0
A65: Depreciation Y5 | F65: 0 | G65: 0 | H65: 0 | I65: 0 | J65: 0 | N65: --> take care to add taxes and Cash impact | S65: I | T65: 1 | U65: coeff variation on Trader margin | Y65: (100% default) | AC65: Depreciation Y5 | AD65: =B65/$I$2*$AU$2 -> 0 | AE65: =C65/$I$2*$AU$2 -> 0 | AF65: =D65/$I$2*$AU$2 -> 0 | AG65: =E65/$I$2*$AU$2 -> 0 | AH65: =F65/$I$2*$AU$2 -> 0 | AI65: =G65/$I$2*$AU$2 -> 0 | AJ65: =H65/$I$2*$AU$2 -> 0 | AK65: =I65/$I$2*$AU$2 -> 0 | AL65: =J65/$I$2*$AU$2 -> 0 | AM65: I | AW65: I | AX65: Depreciation Y5 | AY65: =AD65/$AV$7 -> 0 | AZ65: =AE65/$AV$7 -> 0 | BA65: =AF65/$AV$7 -> 0 | BB65: =AG65/$AV$7 -> 0 | BC65: =AH65/$AV$7 -> 0 | BD65: =AI65/$AV$7 -> 0 | BE65: =AJ65/$AV$7 -> 0 | BF65: =AK65/$AV$7 -> 0 | BG65: =AL65/$AV$7 -> 0
A66: Depreciation | B66: 0 | C66: 15.985764 | D66: 15.985764 | E66: 15.985764 | F66: 15.985764 | G66: 15.985764 | H66: 0 | S66: I | T66: =T12 -> 0 | U66: =N52 -> RMB | V66: adapt the simulated price to final price on top | AC66: Depreciation | AD66: =B66/$I$2*$AU$2 -> 0 | AE66: =C66/$I$2*$AU$2 -> 15.985764 | AF66: =D66/$I$2*$AU$2 -> 15.985764 | AG66: =E66/$I$2*$AU$2 -> 15.985764 | AH66: =F66/$I$2*$AU$2 -> 15.985764 | AI66: =G66/$I$2*$AU$2 -> 15.985764 | AJ66: =H66/$I$2*$AU$2 -> 0 | AM66: I | AW66: I | AX66: Depreciation | AY66: =AD66/$AV$7 -> 0 | AZ66: =AE66/$AV$7 -> 1.9982204 | BA66: =AF66/$AV$7 -> 1.9982204 | BB66: =AG66/$AV$7 -> 1.9982204 | BC66: =AH66/$AV$7 -> 1.9982204 | BD66: =AI66/$AV$7 -> 1.9982204 | BE66: =AJ66/$AV$7 -> 0
M67: Simulation /plant & cession price estimation in | N67: RMB | O67: --> see on the right side | S67: I | W67: Simulation /plant & cession price estimation in | X67: =N67 -> RMB | AM67: I | AW67: I
B68: 2025 | C68: 2026 | D68: 2027 | E68: 2028 | F68: 2029 | G68: 2030 | H68: 2031 | N68: Minimum selling price EXW | S68: I | X68: Minimum selling price EXW | AD68: 2023 | AE68: 2024 | AF68: 2025 | AG68: 2026 | AH68: 2027 | AI68: 2028 | AJ68: 2029 | AM68: I | AW68: I | AY68: 2023 | AZ68: 2024 | BA68: 2025 | BB68: 2026 | BC68: 2027 | BD68: 2028 | BE68: 2029
A69: AP | B69: 0 | C69: 33.619635 | D69: 33.619635 | E69: 33.619635 | F69: 33.619635 | G69: 33.619635 | H69: 0 | L69: RM+Trp+Tx | M69: DC | N69: /u | O69: /kg | P69: margin% | Q69: margin | S69: I | V69: RM+Trp+Tx | W69: DC | X69: /u | Y69: /kg | Z69: margin% | AA69: margin | AC69: AP | AD69: =+AE69/AE$2*AD$2 -> 0 | AE69: =C69/C$2*AE$2 -> 33.619635 | AF69: =D69/D$2*AF$2 -> 33.619635 | AG69: =E69/E$2*AG$2 -> 33.619635 | AH69: =F69/F$2*AH$2 -> 33.619635 | AI69: =+AH69/AH$2*AI$2 -> 33.619635 | AJ69: =+AI69/AI$2*AJ$2 -> 0 | AM69: I | AW69: I | AX69: AP | AY69: =AD69/$AV$7 -> 0 | AZ69: =AE69/$AV$7 -> 4.2024543 | BA69: =AF69/$AV$7 -> 4.2024543 | BB69: =AG69/$AV$7 -> 4.2024543 | BC69: =AH69/$AV$7 -> 4.2024543 | BD69: =AI69/$AV$7 -> 4.2024543 | BE69: =AJ69/$AV$7 -> 0
A70: AR | B70: 0 | C70: -109.57261 | D70: -109.57261 | E70: -109.57261 | F70: -109.57261 | G70: -109.57261 | H70: 0 | J70: black-mix | K70: Frankfurt | L70: 0.096070421 | M70: 0.017927223 | N70: 0.2001171 | O70: 54.018883 | P70: 0.43034531 | S70: I | T70: black-mix | U70: =K70 -> Frankfurt | V70: =L70 -> 0.096070421 | W70: =M70 -> 0.017927223 | X70: =N70*T63 -> 0.4002342 | Y70: =O70*T63 -> 108.03777 | Z70: =(X70-(V70+W70))/X70 -> 0.71517266 | AC70: AR | AD70: =+AE70/AE$2*AD$2 -> 0 | AE70: =C70/C$2*AE$2 -> -109.57261 | AF70: =D70/D$2*AF$2 -> -109.57261 | AG70: =E70/E$2*AG$2 -> -109.57261 | AH70: =F70/F$2*AH$2 -> -109.57261 | AI70: =+AH70/AH$2*AI$2 -> -109.57261 | AJ70: =+AI70/AI$2*AJ$2 -> 0 | AM70: I | AW70: I | AX70: AR | AY70: =AD70/$AV$7 -> 0 | AZ70: =AE70/$AV$7 -> -13.696576 | BA70: =AF70/$AV$7 -> -13.696576 | BB70: =AG70/$AV$7 -> -13.696576 | BC70: =AH70/$AV$7 -> -13.696576 | BD70: =AI70/$AV$7 -> -13.696576 | BE70: =AJ70/$AV$7 -> 0
A71: FP | B71: 0 | C71: -41.626117 | D71: -41.626117 | E71: -41.626117 | F71: -41.626117 | G71: -41.626117 | H71: 0 | J71: Pressing-baking | K71: Tianjin | L71: 0 | M71: 0 | N71: 0 | P71: - | Q71: 0 | S71: I | T71: Pressing-baking | U71: =K71 -> Tianjin | V71: =L71+IF(K70=K71,0,X70-N70) -> 0.2001171 | W71: =M71 -> 0 | X71: =N71*T64 -> 0 | Z71: =(X71-(V71+W71))/X71 -> #DIV/0! | AA71: =X71-W71-V71 -> -0.2001171 | AC71: FP | AD71: =+AE71/AE$2*AD$2 -> 0 | AE71: =C71/C$2*AE$2 -> -41.626117 | AF71: =D71/D$2*AF$2 -> -41.626117 | AG71: =E71/E$2*AG$2 -> -41.626117 | AH71: =F71/F$2*AH$2 -> -41.626117 | AI71: =+AH71/AH$2*AI$2 -> -41.626117 | AJ71: =+AI71/AI$2*AJ$2 -> 0 | AM71: I | AW71: I | AX71: FP | AY71: =AD71/$AV$7 -> 0 | AZ71: =AE71/$AV$7 -> -5.2032646 | BA71: =AF71/$AV$7 -> -5.2032646 | BB71: =AG71/$AV$7 -> -5.2032646 | BC71: =AH71/$AV$7 -> -5.2032646 | BD71: =AI71/$AV$7 -> -5.2032646 | BE71: =AJ71/$AV$7 -> 0
A72: WIP | B72: 0 | C72: -4.1293066 | D72: -4.1293066 | E72: -4.1293066 | F72: -4.1293066 | G72: -4.1293066 | H72: 0 | J72: finisher | K72: Tianjin | L72: 0.68253275 | M72: 0.1796938 | N72: 1.3331334 | P72: 0.35323309 | Q72: 0.47090681 | S72: I | T72: finisher | U72: =K72 -> Tianjin | V72: =L72+IF(K71=K72,IF(K72=K70,0,X70-N70),X71-N71) -> 0.88264985 | W72: =M72 -> 0.1796938 | X72: =W75 -> 0 | Z72: =(X72-(V72+W72))/X72 -> #DIV/0! | AA72: =X72-W72-V72 -> -1.0623437 | AC72: WIP | AD72: =+AE72/AE$2*AD$2 -> 0 | AE72: =C72/C$2*AE$2 -> -4.1293066 | AF72: =D72/D$2*AF$2 -> -4.1293066 | AG72: =E72/E$2*AG$2 -> -4.1293066 | AH72: =F72/F$2*AH$2 -> -4.1293066 | AI72: =+AH72/AH$2*AI$2 -> -4.1293066 | AJ72: =+AI72/AI$2*AJ$2 -> 0 | AM72: I | AW72: I | AX72: WIP | AY72: =AD72/$AV$7 -> 0 | AZ72: =AE72/$AV$7 -> -0.51616333 | BA72: =AF72/$AV$7 -> -0.51616333 | BB72: =AG72/$AV$7 -> -0.51616333 | BC72: =AH72/$AV$7 -> -0.51616333 | BD72: =AI72/$AV$7 -> -0.51616333 | BE72: =AJ72/$AV$7 -> 0
A73: RM | B73: 0 | C73: -35.575906 | D73: -35.575906 | E73: -35.575906 | F73: -35.575906 | G73: -35.575906 | H73: 0 | S73: I | AC73: RM | AD73: =+AE73/AE$2*AD$2 -> 0 | AE73: =C73/C$2*AE$2 -> -35.575906 | AF73: =D73/D$2*AF$2 -> -35.575906 | AG73: =E73/E$2*AG$2 -> -35.575906 | AH73: =F73/F$2*AH$2 -> -35.575906 | AI73: =+AH73/AH$2*AI$2 -> -35.575906 | AJ73: =+AI73/AI$2*AJ$2 -> 0 | AM73: I | AW73: I | AX73: RM | AY73: =AD73/$AV$7 -> 0 | AZ73: =AE73/$AV$7 -> -4.4469882 | BA73: =AF73/$AV$7 -> -4.4469882 | BB73: =AG73/$AV$7 -> -4.4469882 | BC73: =AH73/$AV$7 -> -4.4469882 | BD73: =AI73/$AV$7 -> -4.4469882 | BE73: =AJ73/$AV$7 -> 0
A74: TWC | B74: 0 | C74: -157.2843 | D74: -157.2843 | E74: -157.2843 | F74: -157.2843 | G74: -157.2843 | H74: 0 | L74: ship. I & O | M74: cost /u | N74: Minimuim selling price | P74: EXW | S74: I | V74: ship. I & O | W74: cost /u | X74: Minimuim selling price | Z74: =P74 -> EXW | AC74: TWC | AD74: =+SUM(AD69:AD73) -> 0 | AE74: =+SUM(AE69:AE73) -> -157.2843 | AF74: =+SUM(AF69:AF73) -> -157.2843 | AG74: =+SUM(AG69:AG73) -> -157.2843 | AH74: =+SUM(AH69:AH73) -> -157.2843 | AI74: =+SUM(AI69:AI73) -> -157.2843 | AJ74: =+SUM(AJ69:AJ73) -> 0 | AM74: I | AW74: I | AX74: TWC | AY74: =AD74/$AV$7 -> 0 | AZ74: =AE74/$AV$7 -> -19.660537 | BA74: =AF74/$AV$7 -> -19.660537 | BB74: =AG74/$AV$7 -> -19.660537 | BC74: =AH74/$AV$7 -> -19.660537 | BD74: =AI74/$AV$7 -> -19.660537 | BE74: =AJ74/$AV$7 -> 0
A75: DTWC | B75: 0 | C75: -157.2843 | D75: 0 | E75: 0 | F75: 0 | G75: 0 | H75: 157.2843 | J75: Trader | K75: No | L75: 0 | M75: 1.3331334 | N75: 1.3331334 | P75: 0 | Q75: 0 | S75: I | T75: Trader | U75: =K75 -> No | V75: =L75 -> 0 | W75: =X75*IF(K75="No",1,T65*0.95)-V75 -> 0 | X75: =T66 -> 0 | Z75: =(X75-(V75+W75))/X75 -> #DIV/0! | AA75: =X75-W75-V75 -> 0 | AC75: DTWC | AD75: 0 | AE75: =+AE74-AD74 -> -157.2843 | AF75: =+AF74-AE74 -> 0 | AG75: =+AG74-AF74 -> 0 | AH75: =+AH74-AG74 -> 0 | AI75: =+AI74-AH74 -> 0 | AJ75: =+AJ74-AI74 -> 157.2843 | AM75: I | AW75: I | AX75: DTWC | AY75: =AD75/$AV$7 -> 0 | AZ75: =AE75/$AV$7 -> -19.660537 | BA75: =AF75/$AV$7 -> 0 | BB75: =AG75/$AV$7 -> 0 | BC75: =AH75/$AV$7 -> 0 | BD75: =AI75/$AV$7 -> 0 | BE75: =AJ75/$AV$7 -> 19.660537
S76: I | AM76: I | AW76: I
B77: #DIV/0! | C77: -0.23596184 | D77: -0.23596184 | E77: -0.23596184 | F77: -0.23596184 | G77: -0.23596184 | H77: #DIV/0! | S77: I | AD77: =+AD74/AD8 -> #DIV/0! | AE77: =+AE74/AE8 -> #DIV/0! | AF77: =+AF74/AF8 -> #DIV/0! | AG77: =+AG74/AG8 -> #DIV/0! | AH77: =+AH74/AH8 -> #DIV/0! | AI77: =+AI74/AI8 -> #DIV/0! | AJ77: =+AJ74/AJ8 -> #DIV/0! | AM77: I | AW77: I | AY77: =+AY74/AY8 -> #DIV/0! | AZ77: =+AZ74/AZ8 -> #DIV/0! | BA77: =+BA74/BA8 -> #DIV/0! | BB77: =+BB74/BB8 -> #DIV/0! | BC77: =+BC74/BC8 -> #DIV/0! | BD77: =+BD74/BD8 -> #DIV/0! | BE77: =+BE74/BE8 -> #DIV/0!
S78: I | W78: Simulation /plant & cession price estimation in | X78: =Q52 -> EUR | AM78: I | AW78: I
S79: I | X79: Minimum selling price EXW | AM79: I | AW79: I
S80: I | V80: RM+Trp+Tx | W80: DC | X80: /u | Y80: /kg | Z80: margin% | AA80: margin | AM80: I | AW80: I
S81: I | T81: black-mix | U81: =U70 -> Frankfurt | V81: =V70/'RFQ Data'!$K$23 -> 0.012008803 | W81: =W70/'RFQ Data'!$K$23 -> 0.0022409029 | X81: =X70/'RFQ Data'!$K$23 -> 0.050029275 | Y81: =Y70/'RFQ Data'!$K$23 -> 13.504721 | Z81: =Z70 -> 0.71517266 | AM81: I | AW81: I
S82: I | T82: Pressing-baking | U82: =U71 -> Tianjin | V82: =V71/'RFQ Data'!$K$23 -> 0.025014638 | W82: =W71/'RFQ Data'!$K$23 -> 0 | X82: =X71/'RFQ Data'!$K$23 -> 0 | Z82: =Z71 -> #DIV/0! | AA82: =AA71/'RFQ Data'!$K$23 -> -0.025014638 | AM82: I | AW82: I
S83: I | T83: finisher | U83: =U72 -> Tianjin | V83: =V72/'RFQ Data'!$K$23 -> 0.11033123 | W83: =W72/'RFQ Data'!$K$23 -> 0.022461725 | X83: =X72/'RFQ Data'!$K$23 -> 0 | Z83: =Z72 -> #DIV/0! | AA83: =AA72/'RFQ Data'!$K$23 -> -0.13279296 | AM83: I | AW83: I
S84: I | AM84: I | AW84: I
S85: I | V85: ship. I & O | W85: cost /u | X85: Minimuim selling price | Z85: =Z74 -> EXW | AM85: I | AW85: I
S86: I | T86: Trader | U86: =U75 -> No | V86: =V75/'RFQ Data'!$K$23 -> 0 | W86: =W75/'RFQ Data'!$K$23 -> 0 | X86: =X75/'RFQ Data'!$K$23 -> 0 | Z86: =Z75 -> #DIV/0! | AA86: =AA75/'RFQ Data'!$K$23 -> 0 | AM86: I | AW86: I
S87: I | AM87: I | AW87: I

Sheet PROCESS & CAPEX
A1: BOM, PROCESS details & CAPEX - Costing process | K1: Riyong/RY5.578.100A Riyong China | L1: Area with fomula
A2: Productivity proposed | B2: 2025 | C2: 2026 | D2: 2027 | E2: 2028 | F2: 2029 | G2: 2030 | H2: RFQ# | K2: 25626-BRU-00
A3: Price/piece RMB | B3: 1.3331334 | C3: 1.3331334 | D3: 1.3331334 | E3: 1.3331334 | F3: 1.3331334 | G3: 1.3331334 | K3: #VALUE!
A4: Qty | B4: 0 | C4: 500 | D4: 500 | E4: 500 | F4: 500 | G4: 500
A6: Business link max | B6: 0 | C6: kRMB | I6: volume effect
A7: Incoterm | B7: recommended : | C7: DDP | D7: China | E7: Quoted : | F7: EXW | G7: Tianjin | I7: 1.151916
A8: Payment terms max | B8: 60 | C8: Net | F8: rate
A9: Invoicing currency | B9: RMB | E9: RMBRMB | F9: 1 | G9: RMB
A11: Indexation on material | C11: RMB | D11: RMB | K11: used | L11: changed | M11: impact / u | N11: new value
A12: Material | B12: Weight in g | C12: Material value /kg | D12: Value in the product | K12: EUR/kg | L12: EUR/kg | M12: =B9 -> RMB | N12: =M12 -> RMB
A13: Copper | B13: 3.1101917 | C13: 69.2 | D13: 0.22419299 | K13: 8.65 | M13: =IF(L13=0,0,(L13*'RFQ Data'!$K$24-C13)*B13/1000) -> 0 | N13: =D13+M13 -> 0.22419299
A14: Silver | B14: 0 | C14: 9096 | D14: 0 | K14: 1137 | M14: =IF(L14=0,0,(L14*'RFQ Data'!$K$24-C14)*B14/1000) -> 0 | N14: =D14+M14 -> 0
A15: Nat Graphite | B15: 3.8565968 | C15: 22.211227 | D15: 0.089228904 | K15: 2.7764034 | M15: =IF(L15=0,0,(L15*'RFQ Data'!$K$24-C15)*B15/1000) -> 0 | N15: =D15+M15 -> 0.089228904
A16: Art Graphite | B16: 0 | C16: 60 | D16: 0 | K16: 7.5 | M16: =IF(L16=0,0,(L16*'RFQ Data'!$K$24-C16)*B16/1000) -> 0 | N16: =D16+M16 -> 0
A17: - | B17: 0 | C17: 0 | D17: 0 | K17: 0 | M17: =IF(L17=0,0,(L17*'RFQ Data'!$K$24-C17)*B17/1000) -> 0 | N17: =D17+M17 -> 0
A18: Other mix | B18: 0 | C18: 176 | D18: 0 | K18: 22 | M18: =IF(L18=0,0,(L18*'RFQ Data'!$K$24-C18)*B18/1000) -> 0 | N18: =D18+M18 -> 0
A19: 0 | B19: 0 | M19: =IF(L19=0,0,(L19*'RFQ Data'!$K$24-C19)*B19/1000) -> 0 | N19: =D19+M19 -> #VALUE!
A20: Indexation on exchange rate | D20: RMB
A21: Purchasing currency | B21: Quoting currency | C21: Exchange rate | D21: Value
A22: EUR | B22: RMB | C22: 8 | D22: 0.37269761
A23: RMB | B23: RMB | C23: 1 | D23: 0.090907272
A24: 0 | B24: RMB | C24: 0 | D24: 0
C25: 0 | D25: 0
C26: 0 | D26: 0
L27: New indexations are taking in account in the profitability simulation
A28: Material cost | E28: 0.42758308 | F28: RMB | H28: CAPEX COST | J28: Margin | L28: Customer PRICE
D29: Scrap | E29: 0.018544195 | F29: RMB | I29: KRMB | J29: 0.1 | M29: =I29 -> KRMB
A30: Description | B30: Comment (imposed supplier; internal?,…) | C30: Qty per product | D30: Plant (user) | E30: Cost | F30: origin of incoterm | I30: TOOLING | K30: needs ? | M30: TOOLING | N30: COMMENT
A31: Copper powder (g) | B31: 0 | C31: 2.332717 | D31: Tianjin | E31: 0.16142402 | F31: Europe | M31: =IF(AND(K31<>0,ISNUMBER(I31)),I31*(1+J$29),"")
A32: Silver powder (g) | B32: 0 | C32: 0 | E32: 0 | F32: Europe | M32: =IF(AND(K32<>0,ISNUMBER(I32)),I32*(1+J$29),"")
A33: Mix with Nat Graphite (g) | B33: 0 | C33: 3.7045768 | D33: Frankfurt | E33: 0.094650661 | M33: =IF(AND(K33<>0,ISNUMBER(I33)),I33*(1+J$29),"")
A34: Mix with Art Graphite (g) | B34: 0 | C34: 0 | E34: 0 | M34: =IF(AND(K34<>0,ISNUMBER(I34)),I34*(1+J$29),"")
A35: Cu/Ag powder conversion (g) | B35: 0 | C35: 2.332717 | D35: Tianjin | E35: 0.055985209 | F35: Europe | M35: =IF(AND(K35<>0,ISNUMBER(I35)),I35*(1+J$29),"")
A36: Other mix (g) | B36: 0 | C36: 0 | E36: 0 | F36: Europe | M36: =IF(AND(K36<>0,ISNUMBER(I36)),I36*(1+J$29),"")
A37: impregnation material (g) | B37: 0 | C37: 0 | E37: 0 | M37: =IF(AND(K37<>0,ISNUMBER(I37)),I37*(1+J$29),"")
A38: Cable-material (g) | B38: 0 | C38: 0.68175 | D38: Tianjin | E38: 0.0471771 | F38: China + South pacific | M38: =IF(AND(K38<>0,ISNUMBER(I38)),I38*(1+J$29),"")
A39: Cable-conversion (g) | B39: 0 | C39: 0.68175 | D39: Tianjin | E39: 0.0369963 | F39: China + South pacific | M39: =IF(AND(K39<>0,ISNUMBER(I39)),I39*(1+J$29),"")
A40: Grade from Plate | B40: 0 | C40: 0 | E40: 0 | F40: Europe | M40: =IF(AND(K40<>0,ISNUMBER(I40)),I40*(1+J$29),"")
A41: Sleeves (mm) | B41: 0 | C41: 0 | E41: 0 | F41: China + South pacific | I41: 0 | M41: =IF(AND(K41<>0,ISNUMBER(I41)),I41*(1+J$29),"")
A42: specific terminal 1 | B42: 0 | C42: 0 | E42: 0 | F42: China + South pacific | I42: 8.125 | K42: x | M42: =IF(AND(K42<>0,ISNUMBER(I42)),I42*(1+J$29),"") -> 8.9375
A43: specific terminal 2 | B43: 0 | C43: 0 | E43: 0 | F43: China + South pacific | I43: 0 | K43: x | M43: =IF(AND(K43<>0,ISNUMBER(I43)),I43*(1+J$29),"") -> 0
A44: Spring | B44: 0 | C44: 0 | E44: 0 | F44: China + South pacific | I44: 0 | M44: =IF(AND(K44<>0,ISNUMBER(I44)),I44*(1+J$29),"")
A45: Pop off (sub-assembly) | B45: 0 | C45: 0 | E45: 0 | F45: China + South pacific | I45: 0 | M45: =IF(AND(K45<>0,ISNUMBER(I45)),I45*(1+J$29),"")
A46: Alarm wire | B46: 0 | C46: 0 | E46: 0 | F46: China + South pacific | I46: 0 | M46: =IF(AND(K46<>0,ISNUMBER(I46)),I46*(1+J$29),"")
A47: Other component | B47: 0 | C47: 0 | E47: 0 | F47: China + South pacific | I47: 0 | K47: x | M47: =IF(AND(K47<>0,ISNUMBER(I47)),I47*(1+J$29),"") -> 0
A48: Cement powder (g) | B48: 0 | C48: 0 | E48: 0 | F48: Europe | M48: =IF(AND(K48<>0,ISNUMBER(I48)),I48*(1+J$29),"")
A49: Copper powder (g) grinded | B49: Lost in process | C49: 0.09572471 | D49: Tianjin | E49: 0.0066241499 | M49: =IF(AND(K49<>0,ISNUMBER(I49)),I49*(1+J$29),"")
A50: Silver powder (g) grinded | B50: Lost in process | C50: 0 | E50: 0 | M50: =IF(AND(K50<>0,ISNUMBER(I50)),I50*(1+J$29),"")
A51: Mix with Nat Graphite (g) grinded | B51: Lost in process | C51: 0.15201996 | D51: Frankfurt | E51: 0.0038840575 | M51: =IF(AND(K51<>0,ISNUMBER(I51)),I51*(1+J$29),"")
A52: Mix with Art Graphite (g) grinded | B52: Lost in process | C52: 0 | E52: 0 | M52: =IF(AND(K52<>0,ISNUMBER(I52)),I52*(1+J$29),"")
A53: Cu/Ag powder conversion (g) grinded | B53: Lost in process | C53: 0.09572471 | D53: Tianjin | E53: 0.002297393 | M53: =IF(AND(K53<>0,ISNUMBER(I53)),I53*(1+J$29),"")
A54: Other mix (g) grinded | B54: Lost in process | C54: 0 | E54: 0 | M54: =IF(AND(K54<>0,ISNUMBER(I54)),I54*(1+J$29),"")
A55: 0 | B55: 0 | C55: 0 | E55: 0 | F55: 0 | M55: =IF(AND(K55<>0,ISNUMBER(I55)),I55*(1+J$29),"")
A56: 0 | B56: 0 | C56: 0 | E56: 0 | F56: 0 | M56: =IF(AND(K56<>0,ISNUMBER(I56)),I56*(1+J$29),"")
A57: 0 | B57: 0 | C57: 0 | E57: 0 | F57: 0 | M57: =IF(AND(K57<>0,ISNUMBER(I57)),I57*(1+J$29),"")
A58: 0 | B58: 0 | C58: 0 | E58: 0 | F58: 0 | M58: =IF(AND(K58<>0,ISNUMBER(I58)),I58*(1+J$29),"")
A59: Packaging | E59: 0.0030446049 | F59: RMB | L59: Total Tool/RM | M59: =SUM(M31:M58) -> 8.9375
A60: Tansportation | D60: Inbound transportation | E60: 0.055864082 | F60: RMB | J60: x | K60: to be considered
D61: Outbound Transportation | E61: 0.09898122 | F61: RMB | H61: CAPEX COST | J61: Margin | L61: Customer PRICE | R61: margin
A62: Product added value (Labor + VOH) | E62: 0.19762103 | F62: RMB | G62: on max vol | H62: KRMB | I62: KRMB | J62: 0.1 | K62: 0.1 | L62: =H62 -> KRMB | M62: =I62 -> KRMB | O62: =H62 -> KRMB | R62: =J62 -> 0.1
A63: Operation | B63: Machine / comment | C63: # of operation per piece | D63: Plant | E63: Labor Cost | F63: VOH Cost | G63: Machine load (%) | H63: MACHINE | I63: TOOLING | J63: on Mach | K63: on Tool | L63: MACHINE | M63: TOOLING | N63: COMMENT | O63: Cost of a full machine | R63: Price for a full machine (without tooling) | S63: full capcity /mach (Kp/y)
A64: Black mixing | B64: 0 | C64: 1 | D64: Frankfurt | E64: 0.011648478 | F64: 0.0062787452 | G64: 0.015618769 | H64: 14.994018 | I64: 0 | L64: =IF(J64<>0,H64*(1+J$62),"") | M64: =IF(K64<>0,I64*(1+K$62),"") | O64: =IF(G64<>0,H64/G64/(1+$H$92),0) -> 800 | R64: =O64*(1+$J$62) -> 880 | S64: NA
A65: Final mixing | B65: 0 | C65: 1 | D65: Tianjin | E65: 0.0007498019 | F65: 0.0008735066 | G65: 0.0012622928 | H65: 0.24236021 | I65: 0 | L65: =IF(J65<>0,H65*(1+J$62),"") | M65: =IF(K65<>0,I65*(1+K$62),"") | O65: =IF(G65<>0,H65/G65/(1+$H$92),0) -> 160 | R65: =O65*(1+$J$62) -> 176 | S65: NA
A66: Pressing | B66: 0 | C66: 1 | D66: Tianjin | E66: 0.0075387398 | F66: 0.025897464 | G66: 0.050765925 | H66: 29.241173 | I66: 50.4 | K66: x | L66: =IF(J66<>0,H66*(1+J$62),"") | M66: =IF(K66<>0,I66*(1+K$62),"") -> 55.44 | O66: =IF(G66<>0,H66/G66/(1+$H$92),0) -> 480 | R66: =O66*(1+$J$62) -> 528 | S66: =IF(G66<>0,AVERAGE('RFQ Data'!$D$13:$H$13)/G66,"-") -> 9849.1262
A67: Baking (continus) | B67: 0 | C67: 0 | E67: 0 | F67: 0 | G67: 0 | H67: 0 | I67: 0 | L67: =IF(J67<>0,H67*(1+J$62),"") | M67: =IF(K67<>0,I67*(1+K$62),"") | O67: =IF(G67<>0,H67/G67/(1+$H$92),0) -> 0 | R67: =O67*(1+$J$62) -> 0 | S67: =IF(G67<>0,AVERAGE('RFQ Data'!$D$13:$H$13)/G67,"-") -> -
A68: Baking (batch) | B68: 0 | C68: 1 | D68: Tianjin | E68: 0.005963547 | F68: 0.063804312 | G68: 0.14342345 | H68: 27.537302 | I68: 0 | L68: =IF(J68<>0,H68*(1+J$62),"") | M68: =IF(K68<>0,I68*(1+K$62),"") | O68: =IF(G68<>0,H68/G68/(1+$H$92),0) -> 160 | R68: =O68*(1+$J$62) -> 176 | S68: =IF(G68<>0,AVERAGE('RFQ Data'!$D$13:$H$13)/G68,"-") -> 3486.1803
A69: Welding auto | B69: 0 | C69: 0 | E69: 0 | F69: 0 | G69: 0 | H69: 0 | I69: 0 | K69: x | L69: =IF(J69<>0,H69*(1+J$62),"") | M69: =IF(K69<>0,I69*(1+K$62),"") -> 0 | O69: =IF(G69<>0,H69/G69/(1+$H$92),0) -> 0 | R69: =O69*(1+$J$62) -> 0 | S69: =IF(G69<>0,AVERAGE('RFQ Data'!$D$13:$H$13)/G69,"-") -> -
A70: Welding manual | B70: 0 | C70: 0 | E70: 0 | F70: 0 | G70: 0 | H70: 0 | I70: 0 | L70: =IF(J70<>0,H70*(1+J$62),"") | M70: =IF(K70<>0,I70*(1+K$62),"") | O70: =IF(G70<>0,H70/G70/(1+$H$92),0) -> 0 | R70: =O70*(1+$J$62) -> 0 | S70: =IF(G70<>0,AVERAGE('RFQ Data'!$D$13:$H$13)/G70,"-") -> -
A71: Grinding auto | B71: 0 | C71: 0 | E71: 0 | F71: 0 | G71: 0 | H71: 0 | I71: 0 | J71: x | K71: x | L71: =IF(J71<>0,H71*(1+J$62),"") -> 0 | M71: =IF(K71<>0,I71*(1+K$62),"") -> 0 | N71: based on brush grinding machine cost | O71: =IF(G71<>0,H71/G71/(1+$H$92),0) -> 0 | R71: =O71*(1+$J$62) -> 0 | S71: =IF(G71<>0,AVERAGE('RFQ Data'!$D$13:$H$13)/G71,"-") -> -
A72: Grinding manual | B72: 0 | C72: 1 | D72: Tianjin | E72: 0.03 | F72: 0.034626263 | G72: 0.050505051 | H72: 7.7575758 | I72: 0 | L72: =IF(J72<>0,H72*(1+J$62),"") | M72: =IF(K72<>0,I72*(1+K$62),"") | O72: =IF(G72<>0,H72/G72/(1+$H$92),0) -> 128 | R72: =O72*(1+$J$62) -> 140.8 | S72: =IF(G72<>0,AVERAGE('RFQ Data'!$D$13:$H$13)/G72,"-") -> 9900
A73: Impregnation | B73: 0 | C73: 0 | E73: 0 | F73: 0 | G73: 0 | H73: 0 | I73: 0 | L73: =IF(J73<>0,H73*(1+J$62),"") | M73: =IF(K73<>0,I73*(1+K$62),"") | O73: =IF(G73<>0,H73/G73/(1+$H$92),0) -> 0 | R73: =O73*(1+$J$62) -> 0 | S73: =IF(G73<>0,AVERAGE('RFQ Data'!$D$13:$H$13)/G73,"-") -> -
A74: Pop off assembly | B74: 0 | C74: 0 | E74: 0 | F74: 0 | G74: 0 | H74: 0 | I74: 0 | L74: =IF(J74<>0,H74*(1+J$62),"") | M74: =IF(K74<>0,I74*(1+K$62),"") | O74: =IF(G74<>0,H74/G74/(1+$H$92),0) -> 0 | R74: =O74*(1+$J$62) -> 0 | S74: =IF(G74<>0,AVERAGE('RFQ Data'!$D$13:$H$13)/G74,"-") -> -
A75: Drilling/Tamping | B75: 0 | C75: 0 | E75: 0 | F75: 0 | G75: 0 | H75: 0 | I75: 0 | J75: x | L75: =IF(J75<>0,H75*(1+J$62),"") -> 0 | M75: =IF(K75<>0,I75*(1+K$62),"") | O75: =IF(G75<>0,H75/G75/(1+$H$92),0) -> 0 | R75: =O75*(1+$J$62) -> 0 | S75: =IF(G75<>0,AVERAGE('RFQ Data'!$D$13:$H$13)/G75,"-") -> -
A76: Tubing | B76: 0 | C76: 0 | E76: 0 | F76: 0 | G76: 0 | H76: 0 | I76: 0 | L76: =IF(J76<>0,H76*(1+J$62),"") | O76: =IF(G76<>0,H76/G76/(1+$H$92),0) -> 0 | R76: =O76*(1+$J$62) -> 0 | S76: =IF(G76<>0,AVERAGE('RFQ Data'!$D$13:$H$13)/G76,"-") -> -
A77: Terminal welding | B77: 0 | C77: 0 | E77: 0 | F77: 0 | G77: 0 | H77: 0 | I77: 0 | L77: =IF(J77<>0,H77*(1+J$62),"") | O77: =IF(G77<>0,H77/G77/(1+$H$92),0) -> 0 | R77: =O77*(1+$J$62) -> 0 | S77: =IF(G77<>0,AVERAGE('RFQ Data'!$D$13:$H$13)/G77,"-") -> -
A78: Terminal crimping | B78: 0 | C78: 0 | E78: 0 | F78: 0 | G78: 0 | H78: 0 | I78: 0 | K78: x | L78: =IF(J78<>0,H78*(1+J$62),"") | M78: =IF(K78<>0,I78*(1+K$62),"") -> 0 | O78: =IF(G78<>0,H78/G78/(1+$H$92),0) -> 0 | R78: =O78*(1+$J$62) -> 0 | S78: =IF(G78<>0,AVERAGE('RFQ Data'!$D$13:$H$13)/G78,"-") -> -
A79: Tinning manual | B79: 0 | C79: 0 | E79: 0 | F79: 0 | G79: 0 | H79: 0 | I79: 0 | L79: =IF(J79<>0,H79*(1+J$62),"") | M79: =IF(K79<>0,I79*(1+K$62),"") | O79: =IF(G79<>0,H79/G79/(1+$H$92),0) -> 0 | R79: =O79*(1+$J$62) -> 0 | S79: =IF(G79<>0,AVERAGE('RFQ Data'!$D$13:$H$13)/G79,"-") -> -
A80: Plate cutting | B80: 0 | C80: 0 | E80: 0 | F80: 0 | G80: 0 | H80: 0 | I80: 0 | L80: =IF(J80<>0,H80*(1+J$62),"") | M80: =IF(K80<>0,I80*(1+K$62),"") | O80: =IF(G80<>0,H80/G80/(1+$H$92),0) -> 0 | R80: =O80*(1+$J$62) -> 0 | S80: =IF(G80<>0,AVERAGE('RFQ Data'!$D$13:$H$13)/G80,"-") -> -
A81: Block sawing (Auto) | B81: 0 | C81: 0 | E81: 0 | F81: 0 | G81: 0 | H81: 0 | I81: 0 | L81: =IF(J81<>0,H81*(1+J$62),"") | M81: =IF(K81<>0,I81*(1+K$62),"") | O81: =IF(G81<>0,H81/G81/(1+$H$92),0) -> 0 | R81: =O81*(1+$J$62) -> 0 | S81: =IF(G81<>0,AVERAGE('RFQ Data'!$D$13:$H$13)/G81,"-") -> -
A82: Block sizing (Auto) | B82: 0 | C82: 0 | E82: 0 | F82: 0 | G82: 0 | H82: 0 | I82: 0 | L82: =IF(J82<>0,H82*(1+J$62),"") | M82: =IF(K82<>0,I82*(1+K$62),"") | O82: =IF(G82<>0,H82/G82/(1+$H$92),0) -> 0 | R82: =O82*(1+$J$62) -> 0 | S82: =IF(G82<>0,AVERAGE('RFQ Data'!$D$13:$H$13)/G82,"-") -> -
A83: Block finishing (Auto) | B83: 0 | C83: 0 | E83: 0 | F83: 0 | G83: 0 | H83: 0 | I83: 0 | L83: =IF(J83<>0,H83*(1+J$62),"") | M83: =IF(K83<>0,I83*(1+K$62),"") | O83: =IF(G83<>0,H83/G83/(1+$H$92),0) -> 0 | R83: =O83*(1+$J$62) -> 0 | S83: =IF(G83<>0,AVERAGE('RFQ Data'!$D$13:$H$13)/G83,"-") -> -
A84: Block finishing (Manual) | B84: 0 | C84: 0 | E84: 0 | F84: 0 | G84: 0 | H84: 0 | I84: 0 | L84: =IF(J84<>0,H84*(1+J$62),"") | M84: =IF(K84<>0,I84*(1+K$62),"") | O84: =IF(G84<>0,H84/G84/(1+$H$92),0) -> 0 | R84: =O84*(1+$J$62) -> 0 | S84: =IF(G84<>0,AVERAGE('RFQ Data'!$D$13:$H$13)/G84,"-") -> -
A85: Curing | B85: 0 | C85: 0 | E85: 0 | F85: 0 | G85: 0 | H85: 0 | I85: 0 | L85: =IF(J85<>0,H85*(1+J$62),"") | M85: =IF(K85<>0,I85*(1+K$62),"") | O85: =IF(G85<>0,H85/G85/(1+$H$92),0) -> 0 | R85: =O85*(1+$J$62) -> 0 | S85: =IF(G85<>0,AVERAGE('RFQ Data'!$D$13:$H$13)/G85,"-") -> -
A86: Gluing | B86: Glue in VOH | C86: 0 | E86: 0 | F86: 0 | G86: 0 | H86: 0 | I86: 0 | L86: =IF(J86<>0,H86*(1+J$62),"") | M86: =IF(K86<>0,I86*(1+K$62),"") | O86: =IF(G86<>0,H86/G86/(1+$H$92),0) -> 0 | R86: =O86*(1+$J$62) -> 0 | S86: =IF(G86<>0,AVERAGE('RFQ Data'!$D$13:$H$13)/G86,"-") -> -
A87: Taping | B87: 0 | C87: 0 | E87: 0 | F87: 0 | G87: 0 | H87: 0 | I87: 0 | L87: =IF(J87<>0,H87*(1+J$62),"") | M87: =IF(K87<>0,I87*(1+K$62),"") | O87: =IF(G87<>0,H87/G87/(1+$H$92),0) -> 0 | R87: =O87*(1+$J$62) -> 0 | S87: =IF(G87<>0,AVERAGE('RFQ Data'!$D$13:$H$13)/G87,"-") -> -
A88: Standard Brush assembly | B88: 0 | C88: 0 | E88: 0 | F88: 0 | G88: 0 | H88: 0 | I88: 0 | L88: =IF(J88<>0,H88*(1+J$62),"") | O88: =IF(G88<>0,H88/G88/(1+$H$92),0) -> 0 | R88: =O88*(1+$J$62) -> 0 | S88: =IF(G88<>0,AVERAGE('RFQ Data'!$D$13:$H$13)/G88,"-") -> -
A89: Visual check | B89: 0 | C89: 0 | E89: 0 | F89: 0 | G89: 0 | H89: 0 | I89: 0 | L89: =IF(J89<>0,H89*(1+J$62),"") | M89: =IF(K89<>0,I89*(1+K$62),"") | O89: =IF(G89<>0,H89/G89/(1+$H$92),0) -> 0 | R89: =O89*(1+$J$62) -> 0 | S89: =IF(G89<>0,AVERAGE('RFQ Data'!$D$13:$H$13)/G89,"-") -> - | X89: 1.4
A90: F. Packaging | B90: 0 | C90: 1 | D90: Tianjin | E90: 0.0048382594 | F90: 0.0054019085 | G90: 0.0081452179 | H90: 0.15638818 | I90: 0 | L90: =IF(J90<>0,H90*(1+J$62),"") | M90: =IF(K90<>0,I90*(1+K$62),"") | O90: =IF(G90<>0,H90/G90/(1+$H$92),0) -> 16 | R90: =O90*(1+$J$62) -> 17.6 | S90: NA
A91: Trading | B91: 0 | C91: 0 | E91: 0 | F91: 0 | G91: 0 | H91: 0 | I91: 0 | L91: =IF(J91<>0,H91*(1+J$62),"") | M91: =IF(K91<>0,I91*(1+K$62),"") | O91: =IF(G91<>0,H91/G91/(1+$H$92),0) -> 0 | R91: =O91*(1+$J$62) -> 0 | S91: NA
A92: In Europe, some operations would be subcontracted in Tunisia (costing remains unchanged) | G92: with | H92: 0.2 | I92: free capacity | L92: =SUM(L64:L91) -> 0 | M92: =SUM(M64:M91) -> 55.44
A93: PROCESS PARAMETERS (Hyp) | B93: (valid only if the process exist for the brush quoted) | F93: PRODUCT PARAMETERS | O93: PRESS TOOLING COST (EUROS) | V93: total | W93: =K62 -> 0.1 | Y93: total | Z93: 0.1
A94: PRESSING | B94: Press type | C94: see prod. plant | D94: Xxx | E94: type | H94: T | I94: 7 | L94: mm | O94: general case , not for micro-brush | S94: For Low Runner | V94: 3021 | W94: =V94*(1+$W$93) -> 3323.1 | X94: EUR | Y94: =3021*1.4 -> 4229.4 | Z94: =Y94*(1+$W$93) -> 4652.34 | AA94: KWON
B95: Nb of Cavities | D95: 5 | E95: qty | H95: A | I95: 10 | L95: mm | O95: Number of cavities has no impact | S95: For Middle Runner | V95: 5426 | W95: =V95*(1+$W$93) -> 5968.6 | X95: EUR | Y95: =5426*1.4 -> 7596.4 | Z95: =Y95*(1+$W$93) -> 8356.04 | AA95: KWON
B96: Pressure | D96: 42.6 | E96: KN/cm² | H96: R | I96: 28 | L96: mm | S96: For High Runner | V96: 6300 | W96: =V96*(1+$W$93) -> 6930 | X96: EUR | Y96: =6300*1.4 -> 8820 | Z96: =Y96*(1+$W$93) -> 9702 | AA96: KWON
B97: Force /cavity | D97: 83.496 | E97: KN | H97: Cable section | I97: 1.5 | L97: mm² | O97: details for 7 cavities : | S97: 1st set | T97: 2nd set | U97: 3rd set | Y97: 1st set | Z97: 2nd set | AA97: 3rd set
B98: Press Force | D98: 417.48 | E98: KN | H98: Cable Lenght (outside the brush) | I98: 41 | L98: mm
B99: Press speed rate | D99: 8.3777788 | E99: Str/min | H99: Wire material | I99: Cu | O99: One set of tools costs: approx. 2405€. | S99: =SUM(S100:S110) -> 3021 | T99: =SUM(T100:T108) -> 2405 | U99: =SUM(U100:U108) -> 874 | Y99: =SUM(Y100:Y110) -> 4229.4 | Z99: =SUM(Z100:Z110) -> 3367 | AA99: =SUM(AA100:AA110) -> 1223.6
B100: Pressing speed | C100: 0.7125 | D100: 358.15004 | E100: Str/h | H100: pressing direction | I100: A | O100: Three sets of tools are needed for each brush
A101: BAKING | B101: Oven Type | D101: H7 | E101: type | H101: Brush process type ? | I101: B-Alt & Auxilairy / t or a | O101: The Die: 1531€ | R101: =1531*1.4 -> 2143.4 | S101: 1531 | T101: 1531 | Y101: =S101*$X$89 -> 2143.4 | Z101: =T101*X$89 -> 2143.4 | AA101: =U101*X$89 -> 0
B102: Duration | D102: 24 | E102: hour | H102: Apps | I102: HVAC blowers | O102: Upper punch: 7 x 33€ = 231€ / | S102: 231 | T102: 231 | U102: 231 | Y102: =S102*X$89 -> 323.4 | Z102: =T102*X$89 -> 323.4 | AA102: =U102*X$89 -> 323.4
...

Sheet Small runner-PRICE
B1: This area will be used as costing if this RFQ is concerned by a small runner or MOQ change | H1: MOQ/order and minimum price
B2: PRICE Simulator for small series | H2: Pricing by annual volume (as costing file), is mostly efficient for more than 1 full batch (full oven) by year.
C3: complete the yellow cell only | H3: Standard MOQ is defined as a batch oven. Lower MOQ can be offered but in this case std GMDC calcualation is not relevant.
C4: Select the Currency | D4: Simulate your Brush : | H4: Find below the costing tool for minimim price versus MOQ (depending of applicattion & brush size)
C5: EUR | D5: t (mm) | E5: ='PROCESS & CAPEX'!I94 -> 7 | H5: Assumption is that no order can be less than | J5: 2100 | K5: Eur | L5: (Target 2500 Eur /invoice)
C6: =HLOOKUP(C5,$J$7:$N$8,2,0)/J8 -> 1 | D6: a (mm) | E6: ='PROCESS & CAPEX'!I95 -> 10 | I6: Currency rate
D7: r (mm) | E7: ='PROCESS & CAPEX'!I96 -> 28 | J7: EUR | K7: RMB | L7: USD | M7: INR | N7: KWON
F8: if you want to balance a other price/u | I8: =QuotingCUR -> RMB | J8: ='RFQ Data'!H22 -> 0.125 | K8: ='RFQ Data'!I22 -> 1 | L8: ='RFQ Data'!J22 -> 0.1375 | M8: ='RFQ Data'!K22 -> 11.875 | N8: ='RFQ Data'!L22 -> 0.195
D9: Price without components | E9: =IF(F9<>"",F9,(PRICE_inCUR-SUM(D10:D15))*_xlfn.XLOOKUP(C5,J7:N7,J8:N8,1,0,)) -> 0.16664167
C10: Sleeves (mm) | D10: ='PROCESS & CAPEX'!E41*Cur_rate -> 0 | E10: =D10*1.2 -> 0 | F10: +margin (20%)
C11: specific terminal 1 | D11: ='PROCESS & CAPEX'!E42*Cur_rate -> 0 | E11: =D11*1.2 -> 0 | F11: "
C12: specific terminal 2 | D12: ='PROCESS & CAPEX'!E43*Cur_rate -> 0 | E12: =D12*1.2 -> 0 | F12: "
C13: Spring | D13: ='PROCESS & CAPEX'!E44*Cur_rate -> 0 | E13: =D13*1.2 -> 0 | F13: "
C14: Pop off (sub-assembly) | D14: ='PROCESS & CAPEX'!E45*Cur_rate -> 0 | E14: =D14*1.2 -> 0 | F14: "
C15: Alarm wire | D15: ='PROCESS & CAPEX'!E46*Cur_rate -> 0 | E15: =D15*1.2 -> 0 | F15: "
D17: V = | E17: =E7*E6*E5/1000 -> 1.96 | F17: cm3
C18: Full batch (oven) | D18: Standard MOQ | E18: =PRICE!N53 -> 13000 | F18: =0.4/E17*60000 -> 12244.898
B19: 0.9 | C19: of batch size as limit of use of SR tool | D19: Min price is | E19: =PRICE_inCUR*Cur_rate -> 1.3331334 | F19: =C5 -> EUR
E20: =IF(E9<>0,E9,(E17^$D$37/$D$38)*(Cur_rate)) -> 0.16664167 | F20: =E20*F18 -> 2040.5103
B21: {=J5*Cur_rate} -> 2100 | C21: =C5&" min must be offered" -> EUR min must be offered | D21: MOQ /order | E21: PRICE/u | F21: min /order (Cur)
C22: fix your small series qty | D22: 120000 | E22: =IF(F22="from costing","Serial price",(F22/$D22)*1) -> Serial price | F22: =IF($D22>=F$18*$B$19,"from costing",F$29*2+LN($D22/$D$29)*(F$20-F$29*2)/LN(F$18/$D$29)+SUM($E$10:$E$15)*D22) -> from costing | I22: check here
C23: fix your small series qty | D23: =D22/2 -> 60000 | E23: =IF(F23="from costing","Serial price",(F23/$D23)*1) -> Serial price | F23: =IF($D23>=F$18*$B$19,"from costing",F$29*2+LN($D23/$D$29)*(F$20-F$29*2)/LN(F$18/$D$29)+SUM($E$10:$E$15)*D23) -> from costing | I23: which min price to use
C24: fix your small series qty | D24: =D23/3 -> 20000 | E24: =IF(F24="from costing","Serial price",(F24/$D24)*1) -> Serial price | F24: =IF($D24>=F$18*$B$19,"from costing",F$29*2+LN($D24/$D$29)*(F$20-F$29*2)/LN(F$18/$D$29)+SUM($E$10:$E$15)*D24) -> from costing
C25: fix your small series qty | D25: =D24/2 -> 10000 | E25: =IF(F25="from costing","Serial price",(F25/$D25)*1) -> 0.19511463 | F25: =IF($D25>=F$18*$B$19,"from costing",F$29*2+LN($D25/$D$29)*(F$20-F$29*2)/LN(F$18/$D$29)+SUM($E$10:$E$15)*D25) -> 1951.1463
C26: fix your small series qty | D26: =D25/2 -> 5000 | E26: =IF(F26="from costing","Serial price",(F26/$D26)*1) -> 0.32905897 | F26: =IF($D26>=F$18*$B$19,"from costing",F$29*2+LN($D26/$D$29)*(F$20-F$29*2)/LN(F$18/$D$29)+SUM($E$10:$E$15)*D26) -> 1645.2948
C27: fix your small series qty | D27: =D26/2 -> 2500 | E27: =IF(F27="from costing","Serial price",(F27/$D27)*1) -> 0.53577734 | F27: =IF($D27>=F$18*$B$19,"from costing",F$29*2+LN($D27/$D$29)*(F$20-F$29*2)/LN(F$18/$D$29)+SUM($E$10:$E$15)*D27) -> 1339.4433
C28: fix your small series qty | D28: =D27/2.5 -> 1000 | E28: =IF(F28="from costing","Serial price",(F28/$D28)*1) -> 0.93512967 | F28: =IF($D28>=F$18*$B$19,"from costing",F$29*2+LN($D28/$D$29)*(F$20-F$29*2)/LN(F$18/$D$29)+SUM($E$10:$E$15)*D28) -> 935.12967
C29: samples+ (single order) | D29: 500 | E29: =(LOG(E17*10,2)/2+1+SUM(E10:E15))*Cur_rate/5 -> 0.62927817 | F29: =IF(ISNUMBER(E29),$D29*E29,"from costing") -> 314.63909
C30: samples | D30: 30 to 100 parts | E30: fixed price | F30: =400*(Cur_rate) -> 400
C32: Choice the MOQ to be offered ? | D32: 12000 | I32: NO | N32: Reminder :
D33: MINIMUN PRICE IS | E33: =IF(F33="from costing","Serial price",(F33/$D32)*1) -> Serial price | F33: =IF($D32>=F$18*$B$19,"from costing",F$29*2+LN($D32/$D$29)*(F$20-F$29*2)/LN(F$18/$D$29)+SUM($E$10:$E$15)*D32) -> from costing | N33: AVOCarbon do not want to have parts in stock not ordered.
E34: Cur /u | F34: T/O /MOQ | N34: That why we need to negotiate first the MOQ versus price with the customer
I35: find here | N35: Then Production will manage stock versus batch size versus number of set up
C36: PRICE Parameters / apps | D36: USED | I36: how balance
D37: 1.1 | I37: the price vs MOQ | K37: YES
D38: 5.8
K39: OK :-)
B40: Commercial strategy recommended :
B41: Use this minimum price and MOQ to improve current situaiton, arguing that AVOCarbon finance fixed strict rules because our cash is a critical topic.
B42: For new project, RFQ with low volume, we are only interesting if we can make a great margin (GMCD is not a good indicator in that case). Prices could be 2 times this minimum price.
D45: Sleeves (mm)
D46: specific terminal 1
D47: specific terminal 2
D48: Spring
D49: Pop off (sub-assembly)
D50: Alarm wire

Sheet Package offer
B2: Tool for calculation of package : | E2: complete/remplace the yellow cells
C4: qty/y | E4: Package offer
B5: Part #1 | C5: 3000 | D5: Kp | E5: =SUM(C5:C15) -> 7485 | F5: Kp | G5: Put the highest volume on part #1
B6: Part #2 | C6: 1000 | D6: Kp | E6: =E$5/C$5*C6 -> 2495 | F6: Kp
B7: Part #3 | C7: 1000 | D7: Kp | E7: =E$5/C$5*C7 -> 2495 | F7: Kp
B8: Part #4 | C8: 50 | D8: Kp | E8: =E$5/C$5*C8 -> 124.75 | F8: Kp
B9: Part #5 | C9: 500 | D9: Kp | E9: =E$5/C$5*C9 -> 1247.5 | F9: Kp
B10: Part #6 | C10: 500 | D10: Kp | E10: =E$5/C$5*C10 -> 1247.5 | F10: Kp
B11: Part #7 | C11: 300 | D11: Kp | E11: =E$5/C$5*C11 -> 748.5 | F11: Kp
B12: Part #8 | C12: 30 | D12: Kp | E12: =E$5/C$5*C12 -> 74.85 | F12: Kp
B13: Part #9 | C13: 5 | D13: Kp | E13: =E$5/C$5*C13 -> 12.475 | F13: Kp
B14: Part #10 | C14: 100 | D14: Kp | E14: =E$5/C$5*C14 -> 249.5 | F14: Kp
B15: Part #11 | C15: 1000 | D15: Kp | E15: =E$5/C$5*C15 -> 2495 | F15: Kp
B16: Part #12 | C16: 5 | D16: Kp | E16: =E$5/C$5*C16 -> 12.475 | F16: Kp
C17: remark : not applicable on a part consider as a small runner = qty/y < 1 batch
A19: Package offer can be consider only if volume of each part# are close (also close design and complecity - close price)
B20: Exemple 1: | C20: basic approach
D21: qty/y | G21: package offer
C22: Part A | D22: 2500 | E22: Kp | F22: OK | G22: 4500 | H22: Kp | I22: the full volume when volumes are close (max 25% difference on smallest)
C23: Part B | D23: 2000 | E23: Kp | F23: OK | G23: 4500 | H23: Kp | I23: the full volume when volumes are close (max 25% difference on smallest) | O23: =(2500-2000)/2000 -> 0.25
C24: Part C | D24: 10 | E24: Kp | F24: NOK | G24: Not applicable on small runner
B27: Example 2: | C27: (improved approach) large package from a subcontractor
D28: final customer | F28: qty/y
C29: Part A | D29: Customer A | F29: 3000 | G29: Kp | H29: 5050 | I29: Kp | J29: here it is the full qty of the package
C30: Part B | D30: Customer A | F30: 1000 | G30: Kp | H30: =H$29/F$29*F30 -> 1683.3333 | I30: Kp | J30: here it is ratio of the corresponding volume / full volume | O30: =(3000-1000)/1000 -> 2
C31: Part C | D31: Customer A | F31: 1000 | G31: Kp | H31: =H$29/F$29*F31 -> 1683.3333 | I31: Kp | J31: here it is ratio of the corresponding volume / full volume | O31: =(3000-1000)/1000 -> 2
C32: Part D | D32: Customer A | F32: 50 | G32: Kp | H32: =H$29/F$29*F32 -> 84.166667 | I32: Kp | J32: here it is ratio of the corresponding volume / full volume
C33: Part E | D33: Customer B | F33: 500 | G33: Kp | H33: 1000 | I33: Kp
C34: Part F | D34: Customer B | F34: 500 | G34: Kp | H34: 1000 | I34: Kp
C36: we need to split by customer
B38: Example 3: | C38: if more complex, with different applications, different brush sizes, different brush complexity and costs, different products..
C39: then Sales need to evalutate how we can calculate a package (with costing team and PLM)
B41: Exemple 4: | C41: case of a starter with 4 brushes = 2 with double layer on the top and 2 on the bottom
C42: (sames as exemple 1 = basic approach)
D43: qty/y | G43: package offer
C44: Part A | D44: 500 | E44: Kp | G44: 1000 | H44: Kp
C45: Part B | D45: 500 | E45: Kp | G45: 1000 | H45: Kp
B47: Example 5: | C47: case of a wiper with 3 brushes = 2 brushes with sames grade + 1 brush with a other grade
C48: (sames as exemple 1 = basic approach)
D49: qty/y | F49: package offer
C50: Part A | D50: 3000 | F50: 4500 | G50: Kp
C51: Part B | D51: 1500 | F51: 4500 | G51: Kp
C53: nota : volume are significatively different but they are linked and go on the same motor.

Sheet Invest principle
A1: update : | B1: Feb 2025

Sheet Costing principle
B2: Previous appraoch | D2: New Approach
B3: (at plant level) | D3: (at group level) | E3: HOW is it EVALUATE ? | F3: What affects the cost ? | G3: How improve it ?
B4: RM | D4: RM (incl. Final Packaging) | E4: - Supplier costs | F4: Raw material cost & Indexation % of main drivers (Cu, silver) Dimension | G4: Change the design
B5: DIRECT | D5: DL | E5: - Direct labor (based on the best standards of the group in term of process) | F5: process routers manual or automatic process plant location | G5: Find a better alternative process
B6: COST | D6: VOH | E6: - standard cost/h for maintenance / plant - spare parts /process (%/year of a new machine value) - energy and tooling cost /process | F6: Energy and tooling cost | G6: Find a better alternative process
C7: Minimun PRICE | D7: tranportation & taxes | E7: - Inbound transportation for RM - Outbound transportation for intercompany flows and shipment to the customer | F7: Supplier location Customer incoterm Taxes | G7: Do it Local for local
B8: GROSS | D8: FOH + Admin | E8: It is a % of the DL + VOH /plant x volume effect = contribution to Fixed costs of the plants and Corporate costs (R&D / SALES / PURCHASES / COSTING / ACCOUNTING…) | F8: Turn Over (Volume effect) DL + VOH cost production plant locations | G8: Agressivity lever = Stategic decision of Olivier/Eric to reduce the contribution on FOH/Admin/Fees. It is arbitrary and disconnected from the cost calculation (rare case)
B9: MARGIN | D9: Fees
D10: Minimum EBITDA | E10: Based on a ROI target /product type and a financial calculation. (ROI = Return on Investment) Money we need to save for a good rentability | F10: Cost of all machines needed for production Serial order Payment conditions Stock and WIP level (incoterm, …) Investments & tooling payment conditions | G10: Frequency of Pick up, EXW incoterm Increase customer participation on Invest Change the ROI target (Olivier/Eric decision) and relaunch the calculation
B11: remark : previous calculated gross margin is NOT comparable to the numbers on the new costing file (it should higher)
B13: THEN THE SITUATION IS AS FOLLOWS :
C15: Case 1 | E15: Case 2
C16: market price < minimum AVO price | E16: market price > minimum AVO price
C17: We need to review our industrial process | E17: Sales job to get the best price
C18: or stategic decision (Agressivity, ROI) | F18: Maximum EBITDA
E19: possible price
E20: market price
B22: AVO min price
F23: Minimum EBITDA
B24: market price | F24: Fees
F25: FOH + Admin
F26: tranportation & taxes
F27: VOH
F28: DL
B29: 0 | F29: RM (incl. Final Packaging)
O64: =IF(G64<>0,H64/G64*(1-'RFQ Data'!$I$36),0) -> 0
O65: =IF(G65<>0,H65/G65*(1-'RFQ Data'!$I$36),0) -> 0
O66: =IF(G66<>0,H66/G66*(1-'RFQ Data'!$I$36),0) -> 0
O67: =IF(G67<>0,H67/G67*(1-'RFQ Data'!$I$36),0) -> 0
O68: =IF(G68<>0,H68/G68*(1-'RFQ Data'!$I$36),0) -> 0
O69: =IF(G69<>0,H69/G69*(1-'RFQ Data'!$I$36),0) -> 0
O70: =IF(G70<>0,H70/G70*(1-'RFQ Data'!$I$36),0) -> 0
O71: =IF(G71<>0,H71/G71*(1-'RFQ Data'!$I$36),0) -> 0
O72: =IF(G72<>0,H72/G72*(1-'RFQ Data'!$I$36),0) -> 0
O73: =IF(G73<>0,H73/G73*(1-'RFQ Data'!$I$36),0) -> 0
O74: =IF(G74<>0,H74/G74*(1-'RFQ Data'!$I$36),0) -> 0
O75: =IF(G75<>0,H75/G75*(1-'RFQ Data'!$I$36),0) -> 0
... O91: =IF(G91<>0,H91/G91*(1-'RFQ Data'!$I$36),0) -> 0

Sheet Samples guideline
A2: GUIDELINE for SAMPLES
B4: Prototype costs stay in the plant which has the benefice of the future production
B5: (customer projects).
B6: Customer order should arrive in this same plant.
B7: Needed internal invoicing must be organized.
B8: Pick-up must be organized to speed up the lead-time.
B10: Where produce the samples ? :
C11: Where it is faster and cheaper to get
C12: Local for local when tool is existing
C13: India is recommended for Starter and Industrial brushes (tamping..)
C14: Tianjin for small brushes
B16: Recommended Prices and Cession prices for Prototypes - BRUSH PL
C17: cust price | D17: Min price | E17: internal cession price
B18: qty (until) | C18: (ex : Europe) | D18: (ex : China) | E18: between AVO plants
B19: 100 | C19: 400 | D19: =C19/2 -> 200 | E19: 100
B20: 200 | C20: 600 | D20: =C20/2 -> 300 | E20: =C20/4 -> 150
B21: 500 | C21: 1000 | D21: =C21/2 -> 500 | E21: =C21/4 -> 250
B22: 2500 | C22: 2500 | D22: =C22/2 -> 1250 | E22: =C22/4 -> 625
C23: EUR | D23: EUR | E23: EUR
E24: + tooling cost
B26: Sales team negotiate with the customer.
B27: If samples failed on customer tests, next samples could be free of charge for the customer (Sales decision)
B28: Between AVOCarbon plants , find a fair deal in the team as the best profit for the group. The group prevails first.
